fifo/define.v
../define.v

fifo/mFifo.v
///////////////////////////////////////////
// This modules is in modakio cpu.
// mArb.v module ver 1.0
// 2019/03/16 writen by denchu
//
`ifndef	_mFIFO_
`define	_mFIFO_
`include "./define.v"

module mFifo #(
	parameter	p_st_bits		= 32,
	parameter	p_fifo_length 		= 8,
	parameter	p_fifo_length_log2 	= 3
//	parameter	p_fifo_length_log2 	= log2(p_fifo_length)
)(
	input	[p_st_bits-1:0]	i_snk_data,
	input			i_snk_valid,
	output			o_snk_ready,
	
	output	[p_st_bits-1:0]	o_src_data,
	output			o_src_valid,
	input			i_src_ready,

	input			clk,
	input			rst

);
	//function integer log2;
        //input integer num;
        //	begin
        //		num = num - 1;
        //	for (log2 = 0; num > 0; log2 = log2 + 1)
        //		num = num >> 1;
        //	end
        //endfunction

	//reg	[p_fifo_length-1:0] 		mem [p_st_bits-1:0];
	reg	[p_st_bits-1:0] 		mem [p_fifo_length-1:0];
	reg	[p_fifo_length_log2-1:0]	w_ptr;
	reg	[p_fifo_length_log2-1:0]	r_ptr;

	// write pointer
	//always @(posedge clk or posedge rst)
	always @(posedge clk)
	begin
		if(rst) begin
			w_ptr <= 0;
		end else if (!w_full && i_snk_valid) begin
			w_ptr <= w_ptr + 1;
		end
	end
	
	// read pointer
	//always @(posedge clk or posedge rst)
	always @(posedge clk)
	begin
		if(rst) begin
			r_ptr <= 0;
		end else if (!w_empty && i_src_ready) begin
			r_ptr <= r_ptr + 1;
		end
	end

	//write buffer
	always @(posedge clk)
	begin
		if (!w_full && i_snk_valid) begin
			mem[w_ptr] <= i_snk_data;
		end
	end
	
	//read buffe
	assign o_src_data = mem[r_ptr];

	wire	w_full;
	assign 	w_full = ((w_ptr + 1 == r_ptr)||((r_ptr == 0) && (w_ptr == p_fifo_length - 1))) ? 1 : 0;
	assign	o_snk_ready = !w_full;

	wire	w_empty;
	assign 	w_empty = (w_ptr == r_ptr)? 1 : 0;
	assign	o_src_valid = !w_empty;
	
	
	
endmodule

`endif

fifo/main.v
`timescale  1ps/1ps

`include "../define.v"
`define WORD_BITS 32

module main;
	reg rst;
	reg clk;
	reg [`INST_BITS-1:0]	data;
	reg valid;


	parameter CYCLE = 1000; //clock rate = 1000ns(1MHz)


	//reset
	initial begin
		//#(CYCLE*0.1)
				rst <= 1;
		#(CYCLE*4)	rst <= 0;
	end

	//clock
	initial begin
		clk <= 0;
	end
	always begin
		#(CYCLE/2) clk <= ~clk;
	end
	
	//count up
	initial begin
		data <= 0;
	end
	always @(posedge clk) begin
		//#(CYCLE*0.1)
			data <= data + 1;
	end
	
	//random
	initial begin
		valid <= 0;
	end
	always @(posedge clk) begin
		#(CYCLE*20)
		valid <= $random % 2;
	end


	integer idx;
	initial begin
		$dumpfile("main.vcd");
		$dumpvars(0, main);
		for(idx = 0; idx < 8; idx = idx + 1) $dumpvars(1, main.uFifo.mem[idx]);
		
		#(CYCLE*100);
			$display(main.uFifo.w_full);
		$finish;
		
	end
	
	mFifo #(
		.p_st_bits		(32),
		.p_fifo_length 		(8),
		.p_fifo_length_log2 	(3)
	) uFifo(
		.i_snk_data		(data),
		//.i_snk_valid		(valid),
		.i_snk_valid		(valid),
		.o_snk_ready		(),
		
		.o_src_data		(),
		.o_src_valid		(),
		.i_src_ready		(!valid),

		.clk			(clk),
		.rst			(rst)

	);


endmodule

fifo/main.vcd
$date
	Thu May  2 17:22:46 2019
$end
$version
	Icarus Verilog
$end
$timescale
	1ps
$end
$scope module main $end
$var reg 1 ! clk $end
$var reg 32 " data [31:0] $end
$var integer 32 # idx [31:0] $end
$var reg 1 $ rst $end
$var reg 1 % valid $end
$scope module uFifo $end
$var wire 1 & clk $end
$var wire 32 ' i_snk_data [31:0] $end
$var wire 1 ( i_snk_valid $end
$var wire 1 ) i_src_ready $end
$var wire 1 * o_snk_ready $end
$var wire 32 + o_src_data [31:0] $end
$var wire 1 , o_src_valid $end
$var wire 1 - rst $end
$var wire 1 . w_empty $end
$var wire 1 / w_full $end
$var reg 3 0 r_ptr [2:0] $end
$var reg 3 1 w_ptr [2:0] $end
$upscope $end
$upscope $end
$scope module main $end
$scope module uFifo $end
$var reg 32 2 \mem[0] [31:0] $end
$upscope $end
$upscope $end
$scope module main $end
$scope module uFifo $end
$var reg 32 3 \mem[1] [31:0] $end
$upscope $end
$upscope $end
$scope module main $end
$scope module uFifo $end
$var reg 32 4 \mem[2] [31:0] $end
$upscope $end
$upscope $end
$scope module main $end
$scope module uFifo $end
$var reg 32 5 \mem[3] [31:0] $end
$upscope $end
$upscope $end
$scope module main $end
$scope module uFifo $end
$var reg 32 6 \mem[4] [31:0] $end
$upscope $end
$upscope $end
$scope module main $end
$scope module uFifo $end
$var reg 32 7 \mem[5] [31:0] $end
$upscope $end
$upscope $end
$scope module main $end
$scope module uFifo $end
$var reg 32 8 \mem[6] [31:0] $end
$upscope $end
$upscope $end
$scope module main $end
$scope module uFifo $end
$var reg 32 9 \mem[7] [31:0] $end
$upscope $end
$upscope $end
$enddefinitions $end
#0
$dumpvars
bx 9
bx 8
bx 7
bx 6
bx 5
bx 4
bx 3
bx 2
b0 1
b0 0
0/
1.
1-
0,
bx +
1*
1)
0(
b0 '
0&
0%
1$
b1000 #
b0 "
0!
$end
#500
b1 "
b1 '
1!
1&
#1000
0!
0&
#1500
b10 "
b10 '
1!
1&
#2000
0!
0&
#2500
b11 "
b11 '
1!
1&
#3000
0!
0&
#3500
b100 "
b100 '
1!
1&
#4000
0!
0&
0$
0-
#4500
b101 "
b101 '
1!
1&
#5000
0!
0&
#5500
b110 "
b110 '
1!
1&
#6000
0!
0&
#6500
b111 "
b111 '
1!
1&
#7000
0!
0&
#7500
b1000 "
b1000 '
1!
1&
#8000
0!
0&
#8500
b1001 "
b1001 '
1!
1&
#9000
0!
0&
#9500
b1010 "
b1010 '
1!
1&
#10000
0!
0&
#10500
b1011 "
b1011 '
1!
1&
#11000
0!
0&
#11500
b1100 "
b1100 '
1!
1&
#12000
0!
0&
#12500
b1101 "
b1101 '
1!
1&
#13000
0!
0&
#13500
b1110 "
b1110 '
1!
1&
#14000
0!
0&
#14500
b1111 "
b1111 '
1!
1&
#15000
0!
0&
#15500
b10000 "
b10000 '
1!
1&
#16000
0!
0&
#16500
b10001 "
b10001 '
1!
1&
#17000
0!
0&
#17500
b10010 "
b10010 '
1!
1&
#18000
0!
0&
#18500
b10011 "
b10011 '
1!
1&
#19000
0!
0&
#19500
b10100 "
b10100 '
1!
1&
#20000
0!
0&
#20500
b10101 "
b10101 '
1!
1&
#21000
0!
0&
#21500
b10110 "
b10110 '
1!
1&
#22000
0!
0&
#22500
b10111 "
b10111 '
1!
1&
#23000
0!
0&
#23500
b11000 "
b11000 '
1!
1&
#24000
0!
0&
#24500
b11001 "
b11001 '
1!
1&
#25000
0!
0&
#25500
b11010 "
b11010 '
1!
1&
#26000
0!
0&
#26500
b11011 "
b11011 '
1!
1&
#27000
0!
0&
#27500
b11100 "
b11100 '
1!
1&
#28000
0!
0&
#28500
b11101 "
b11101 '
1!
1&
#29000
0!
0&
#29500
b11110 "
b11110 '
1!
1&
#30000
0!
0&
#30500
b11111 "
b11111 '
1!
1&
#31000
0!
0&
#31500
b100000 "
b100000 '
1!
1&
#32000
0!
0&
#32500
b100001 "
b100001 '
1!
1&
#33000
0!
0&
#33500
b100010 "
b100010 '
1!
1&
#34000
0!
0&
#34500
b100011 "
b100011 '
1!
1&
#35000
0!
0&
#35500
b100100 "
b100100 '
1!
1&
#36000
0!
0&
#36500
b100101 "
b100101 '
1!
1&
#37000
0!
0&
#37500
b100110 "
b100110 '
1!
1&
#38000
0!
0&
#38500
b100111 "
b100111 '
1!
1&
#39000
0!
0&
#39500
b101000 "
b101000 '
1!
1&
#40000
0!
0&
#40500
1,
0.
b101000 2
b101000 +
b101001 "
b101001 '
b1 1
1!
1&
1%
0)
1(
#41000
0!
0&
#41500
b101010 "
b101010 '
b101001 3
b10 1
1!
1&
#42000
0!
0&
#42500
b101010 4
b101011 "
b101011 '
b11 1
1!
1&
#43000
0!
0&
#43500
b101100 "
b101100 '
b101011 5
b100 1
1!
1&
#44000
0!
0&
#44500
b101100 6
b101101 "
b101101 '
b101 1
1!
1&
#45000
0!
0&
#45500
b101110 "
b101110 '
b101101 7
b110 1
1!
1&
#46000
0!
0&
#46500
0*
1/
b101110 8
b101111 "
b101111 '
b111 1
1!
1&
#47000
0!
0&
#47500
b110000 "
b110000 '
1!
1&
#48000
0!
0&
#48500
b110001 "
b110001 '
1!
1&
#49000
0!
0&
#49500
b110010 "
b110010 '
1!
1&
#50000
0!
0&
#50500
b110011 "
b110011 '
1!
1&
#51000
0!
0&
#51500
b110100 "
b110100 '
1!
1&
#52000
0!
0&
#52500
b110101 "
b110101 '
1!
1&
#53000
0!
0&
#53500
b110110 "
b110110 '
1!
1&
#54000
0!
0&
#54500
b110111 "
b110111 '
1!
1&
#55000
0!
0&
#55500
b111000 "
b111000 '
1!
1&
#56000
0!
0&
#56500
b111001 "
b111001 '
1!
1&
#57000
0!
0&
#57500
b111010 "
b111010 '
1!
1&
#58000
0!
0&
#58500
b111011 "
b111011 '
1!
1&
#59000
0!
0&
#59500
b111100 "
b111100 '
1!
1&
#60000
0!
0&
#60500
b111101 "
b111101 '
1!
1&
#61000
0!
0&
#61500
b111110 "
b111110 '
1!
1&
#62000
0!
0&
#62500
b111111 "
b111111 '
1!
1&
#63000
0!
0&
#63500
b1000000 "
b1000000 '
1!
1&
#64000
0!
0&
#64500
b1000001 "
b1000001 '
1!
1&
#65000
0!
0&
#65500
b1000010 "
b1000010 '
1!
1&
#66000
0!
0&
#66500
b1000011 "
b1000011 '
1!
1&
#67000
0!
0&
#67500
b1000100 "
b1000100 '
1!
1&
#68000
0!
0&
#68500
b1000101 "
b1000101 '
1!
1&
#69000
0!
0&
#69500
b1000110 "
b1000110 '
1!
1&
#70000
0!
0&
#70500
b1000111 "
b1000111 '
1!
1&
#71000
0!
0&
#71500
b1001000 "
b1001000 '
1!
1&
#72000
0!
0&
#72500
b1001001 "
b1001001 '
1!
1&
#73000
0!
0&
#73500
b1001010 "
b1001010 '
1!
1&
#74000
0!
0&
#74500
b1001011 "
b1001011 '
1!
1&
#75000
0!
0&
#75500
b1001100 "
b1001100 '
1!
1&
#76000
0!
0&
#76500
b1001101 "
b1001101 '
1!
1&
#77000
0!
0&
#77500
b1001110 "
b1001110 '
1!
1&
#78000
0!
0&
#78500
b1001111 "
b1001111 '
1!
1&
#79000
0!
0&
#79500
b1010000 "
b1010000 '
1!
1&
#80000
0!
0&
#80500
b1010001 "
b1010001 '
1!
1&
#81000
0!
0&
#81500
b1010010 "
b1010010 '
1!
1&
#82000
0!
0&
#82500
b1010011 "
b1010011 '
1!
1&
#83000
0!
0&
#83500
b1010100 "
b1010100 '
1!
1&
#84000
0!
0&
#84500
b1010101 "
b1010101 '
1!
1&
#85000
0!
0&
#85500
b1010110 "
b1010110 '
1!
1&
#86000
0!
0&
#86500
b1010111 "
b1010111 '
1!
1&
#87000
0!
0&
#87500
b1011000 "
b1011000 '
1!
1&
#88000
0!
0&
#88500
b1011001 "
b1011001 '
1!
1&
#89000
0!
0&
#89500
b1011010 "
b1011010 '
1!
1&
#90000
0!
0&
#90500
b1011011 "
b1011011 '
1!
1&
#91000
0!
0&
#91500
b1011100 "
b1011100 '
1!
1&
#92000
0!
0&
#92500
b1011101 "
b1011101 '
1!
1&
#93000
0!
0&
#93500
b1011110 "
b1011110 '
1!
1&
#94000
0!
0&
#94500
b1011111 "
b1011111 '
1!
1&
#95000
0!
0&
#95500
b1100000 "
b1100000 '
1!
1&
#96000
0!
0&
#96500
b1100001 "
b1100001 '
1!
1&
#97000
0!
0&
#97500
b1100010 "
b1100010 '
1!
1&
#98000
0!
0&
#98500
b1100011 "
b1100011 '
1!
1&
#99000
0!
0&
#99500
b1100100 "
b1100100 '
1!
1&
