define.v
////////////////////////////////
// modakio cpu operation number
// operation number

// func log2
//function integer log2;
//	input integer in;
//	begin
//		in = in - 1;
//		for (log2 = 0; in > 0; log2 = log2+1)
//			in = in >> 1;
//	end
//endfunction



// 
// CalcReg(CR)
// 
`define TYPE_CR		0
// interger
`define	OP_IADD		0
`define	OP_UIADD	1
`define	OP_ISUB		2
`define	OP_UISUB	3
`define	OP_IMUL		4
`define	OP_UIMUL	5
`define	OP_IDEV		6
`define	OP_UIDEV	7

//floating point 
`define	OP_FADD		8
`define	OP_FCMP		9
`define	OP_FSUB		10
`define	OP_CR_NOUSE11	11
`define	OP_FMUL		12
`define	OP_CR_NOUSE13	13
`define	OP_FDEV		14
`define	OP_CR_NOUSE15	15

// 
// LogicReg(LR)
// 
`define TYPE_LR		1

// bit logical

`define	OP_AND		0
`define	OP_OR		1
`define	OP_XOR		2
`define	OP_UCMP		3
`define	OP_LSFT		4
`define	OP_RSFT		5
`define	OP_CMP		6
`define	OP_JR		7

`define	OP_LR_NOUSE8	8
`define	OP_LR_NOUSE9	9
`define	OP_LR_NOUSE10	10
`define	OP_LR_NOUSE11	11
`define	OP_LR_NOUSE12	12
`define	OP_LR_NOUSE13	13
`define	OP_LR_NOUSE14	14
`define	OP_LR_NOUSE15	15


// 
// Immediate
// 
`define TYPE_I		2

`define	OP_IADDI	0
`define	OP_UIADDI	1
`define	OP_ISUBI	2
`define	OP_UISUBI	3
`define	OP_IMULI	4
`define	OP_UIMULI	5
`define	OP_IDEVI	6
`define	OP_UIDEVI	7

`define	OP_LW		8
`define	OP_ST		9
`define	OP_LSFTI	10
`define	OP_RSFTI	11
`define	OP_BE		12
`define	OP_BNE		13
`define	OP_CMPI		14
`define	OP_UCMPI	15


// 
// Jump
// 
`define TYPE_J		3

`define	OP_J		0
`define	OP_JAL		1
`define	OP_J_NOUSE2	2
`define	OP_J_NOUSE3	3
`define	OP_J_NOUSE4	4
`define	OP_J_NOUSE5	5
`define	OP_J_NOUSE6	6
`define	OP_J_NOUSE7	7

`define	OP_J_NOUSE8	8
`define	OP_J_NOUSE9	9
`define	OP_J_NOUSE10	10
`define	OP_J_NOUSE11	11
`define	OP_J_NOUSE12	12
`define	OP_J_NOUSE13	13
`define	OP_J_NOUSE14	14
`define	OP_J_NOUSE15	15

`define	NUM_OF_OP	42

//
// HARDWARE DISCRIPTION
//
`define	NUM_OF_FETCH_INST	4
`define	INST_FIFO_LENGTH	`NUM_OF_FETCH_INST * 2

`define WORD_BITS	32
`define	NUM_OF_REG	32
`define REG_ADDR_BITS	5 
`define MEM_ADDR_BITS	18

`define BITS_PER_BYTE	8

`define INST_BITS	`WORD_BITS
`define TYPE_BITS	2
`define OP_BITS		4
`define DST_BITS	5
`define SRC0_BITS	5
`define SRC1_BITS	5
`define MINOR_IMM_BITS	16
`define MAJOR_IMM_BITS	26

`define TYPE_OFFSET	`INST_BITS - `TYPE_BITS
`define OP_OFFSET	`INST_BITS - `TYPE_BITS - `OP_BITS
`define DST_OFFSET	`INST_BITS - `TYPE_BITS - `OP_BITS - `DST_BITS
`define SRC0_OFFSET	`INST_BITS - `TYPE_BITS - `OP_BITS - `DST_BITS - `SRC0_BITS
`define SRC1_OFFSET	`INST_BITS - `TYPE_BITS - `OP_BITS - `DST_BITS - `SRC0_BITS - `SRC1_BITS
`define MINOR_IMM_OFFSET	`INST_BITS - `TYPE_BITS - `OP_BITS - `DST_BITS - `SRC0_BITS - `MINOR_IMM_BITS
`define MAJOR_IMM_OFFSET	`INST_BITS - `TYPE_BITS - `OP_BITS - `MAJOR_IMM_BITS

`define BURST_LENGTH	4

decoder/mDecoder.v
///////////////////////////////////////////
// This modules is in modakio cpu.
// mDecoder.v module ver 1.0
// 2019/03/12 writen by denchu
//
`ifndef	_mDECODER_
`define	_mDECODER_
`include	"./define.v"

module mDecoder (
	input	[`INST_BITS-1:0]	i_inst,
	input				i_inst_valid,
	
	output				o_jr,

	output	[`WORD_BITS-1:0]	o_jal_addr,
	output				o_jal_addr_valid,
	
	output	[`WORD_BITS-1:0]	o_j_addr,
	output				o_j_addr_valid,

	output				o_write_req,
	output				o_read_req,
	
	output	[`TYPE_BITS-1:0]	o_type,
	output	[`OP_BITS-1:0]		o_op,
	output	[`DST_BITS-1:0]		o_dst,
	output	[`SRC0_BITS-1:0]	o_src0,
	output	[`SRC1_BITS-1:0]	o_src1,
	output	[`MINOR_IMM_BITS-1:0]	o_minor_imm,
	
	input	rst,
	input	clk
); 
	wire   [`MAJOR_IMM_BITS-1:0]	w_major_imm;
	wire   [`SRC1_BITS-1:0]		w_src1;

	assign o_jr		= (((o_type == `TYPE_LR) && (o_op == `OP_JR))  && i_inst_valid)? 1 : 0;
	
	assign o_jal_addr	= w_major_imm;
	assign o_jal_addr_valid	= (((o_type == `TYPE_J)  && (o_op == `OP_JAL)) && i_inst_valid) ? 1 : 0;
	
	assign o_j_addr		= w_major_imm;
	assign o_j_addr_valid	= (((o_type == `TYPE_J)  && (o_op == `OP_J))   && i_inst_valid)? 1 : 0;

	assign o_write_req	= (((o_type == `TYPE_I)  && (o_op == `OP_ST)) && i_inst_valid)? 1 : 0;
	assign o_read_req	= (((o_type == `TYPE_I)  && (o_op == `OP_LW)) && i_inst_valid)? 1 : 0;
	
	assign o_type 		= i_inst[     `TYPE_BITS +      `TYPE_OFFSET - 1:     `TYPE_OFFSET];
	assign o_op 		= i_inst[       `OP_BITS +        `OP_OFFSET - 1:       `OP_OFFSET];
	assign o_dst 		= i_inst[      `DST_BITS +       `DST_OFFSET - 1:      `DST_OFFSET];
	assign o_src0 		= i_inst[     `SRC0_BITS +      `SRC0_OFFSET - 1:     `SRC0_OFFSET];
	assign w_src1 		= i_inst[     `SRC1_BITS +      `SRC1_OFFSET - 1:     `SRC1_OFFSET];
	assign o_src1 		= (((o_type == `TYPE_I)&&(o_op == `OP_ST))||((o_type == `TYPE_I)&&(o_op == `OP_BE)))||((o_type == `TYPE_I)&&(o_op == `OP_BNE)) ? o_dst : w_src1;
	assign o_minor_imm 	= i_inst[`MINOR_IMM_BITS + `MINOR_IMM_OFFSET - 1:`MINOR_IMM_OFFSET];
	assign w_major_imm 	= i_inst[`MAJOR_IMM_BITS + `MAJOR_IMM_OFFSET - 1:`MAJOR_IMM_OFFSET];

endmodule

`endif

decoder/main.v
`timescale  1ns/1ns

`include "../define.v"
`define WORD_BITS 32

module main;
	reg rst;
	reg clk;
	reg [`INST_BITS-1:0]	inst;
	reg valid;


	parameter CYCLE = 1000; //clock rate = 1000ns(1MHz)


	//reset
	initial begin
				rst = 1;
		#(CYCLE*4)	rst = 0;
	end

	//clock
	initial begin
		clk = 0;
		end
	always begin
		#(CYCLE/2) clk = ~clk;
	end
	
	//count up
//	initial begin
//		inst = 0;
//		end
//		always @(posedge clk) begin
//			inst = inst + 1;
//		end
//
//	initial begin
	initial begin
		$dumpfile("main.vcd");
		$dumpvars(0, main);
//inst <= 32'h00221800;// iAdd 	K0 K1 R0  
//inst <= 32'h08221800;// iSub 	K0 K1 R0 
//inst <= 32'h10221800;// iMul 	K0 K1 R0  
//inst <= 32'h18221800;// iDev 	K0 K1 R0 
//inst <= 32'h20221800;// fAdd 	K0 K1 R0 
//inst <= 32'h28221800;// fSub 	K0 K1 R0 
//inst <= 32'h30221800;// fMul 	K0 K1 R0 
//inst <= 32'h38221800;// fDev 	K0 K1 R0 
//inst <= 32'h40221800;// and  	K0 K1 R0 
//inst <= 32'h44221800;// or   	K0 K1 R0 
//inst <= 32'h48221800;// xor  	K0 K1 R0 
//inst <= 32'h4c221800;// ucmp  	K0 K1 R0 
//inst <= 32'h50221800;// Lsft 	K0 K1 R0 
//inst <= 32'h54221800;// Rsft 	K0 K1 R0 
//inst <= 32'h58221800;// cmp  	K0 K1 R0 
//inst <= 32'h5c010000;// jr   	K0 K1 R0 
//inst <= 32'h80220003;// iAddi 	K0 K1 3
//inst <= 32'h88220003;// iSubi 	K0 K1 3
//inst <= 32'h90220003;// iMuli 	K0 K1 3
//inst <= 32'h98220003;// iDevi 	K0 K1 3
//inst <= 32'ha0220003;// lw 	K0 K1 3
//inst <= 32'ha4220003;// sw	K0 K1 3
//inst <= 32'ha8220003;// Lsfti 	K0 K1 3
//inst <= 32'hac220003;// Rsfti 	K0 K1 3
//inst <= 32'hb0220003;// be 	K0 K1 0x3
//inst <= 32'hb4220003;// bne 	K0 K1 3
//inst <= 32'hb8220003;// cmpi 	K0 K1 0x3
//inst <= 32'hbc220003;// ucmpi 	K0 K1 0x3
//inst <= 32'hc0000004;// j 	0x4
//inst <= 32'hc4000004;// jal 	0x4                   
		
		valid 	<= 1;
		inst <= 32'h00221800;// iAdd 	K0 K1 R0  
		#(CYCLE*10)
		inst <= 32'h08221800;// iSub 	K0 K1 R0 
		#(CYCLE*10)
		inst <= 32'h10221800;// iMul 	K0 K1 R0  
		#(CYCLE*10)
		inst <= 32'h18221800;// iDev 	K0 K1 R0 
		#(CYCLE*10)
		inst <= 32'h20221800;// fAdd 	K0 K1 R0 
		#(CYCLE*10)
		inst <= 32'h28221800;// fSub 	K0 K1 R0 
		#(CYCLE*10)
		inst <= 32'h30221800;// fMul 	K0 K1 R0 
		#(CYCLE*10)
		inst <= 32'h38221800;// fDev 	K0 K1 R0 
		#(CYCLE*10)
		inst <= 32'h40221800;// and  	K0 K1 R0 
		#(CYCLE*10)
		inst <= 32'h44221800;// or   	K0 K1 R0 
		#(CYCLE*10)
		inst <= 32'h48221800;// xor  	K0 K1 R0 
		#(CYCLE*10)
		inst <= 32'h4c221800;// ucmp  	K0 K1 R0 
		#(CYCLE*10)
		inst <= 32'h50221800;// Lsft 	K0 K1 R0 
		#(CYCLE*10)
		inst <= 32'h54221800;// Rsft 	K0 K1 R0 
		#(CYCLE*10)
		inst <= 32'h58221800;// cmp  	K0 K1 R0 
		#(CYCLE*10)
		inst <= 32'h5c010000;// jr   	K0 K1 R0 
		#(CYCLE*10)
		inst <= 32'h80220003;// iAddi 	K0 K1 3
		#(CYCLE*10)
		inst <= 32'h88220003;// iSubi 	K0 K1 3
		#(CYCLE*10)
		inst <= 32'h90220003;// iMuli 	K0 K1 3
		#(CYCLE*10)
		inst <= 32'h98220003;// iDevi 	K0 K1 3
		#(CYCLE*10)
		inst <= 32'ha0220003;// lw 	K0 K1 3
		#(CYCLE*10)
		inst <= 32'ha4220003;// sw	K0 K1 3
		#(CYCLE*10)
		inst <= 32'ha8220003;// Lsfti 	K0 K1 3
		#(CYCLE*10)
		inst <= 32'hac220003;// Rsfti 	K0 K1 3
		#(CYCLE*10)
		inst <= 32'hb0220003;// be 	K0 K1 0x3
		#(CYCLE*10)
		inst <= 32'hb4220003;// bne 	K0 K1 3
		#(CYCLE*10)
		inst <= 32'hb8220003;// cmpi 	K0 K1 0x3
		#(CYCLE*10)
		inst <= 32'hbc220003;// ucmpi 	K0 K1 0x3
		#(CYCLE*10)
		inst <= 32'hc0000004;// j 	0x4
		#(CYCLE*10)
		inst <= 32'hc4000004;// jal 	0x4                   
		#(CYCLE*10)
		$finish;
	end
	
	mDecoder uDecoder (	
	.i_inst			(inst),
	.i_inst_valid		(valid),
	
	.o_jr			(),

	.o_jal_addr		(),
	.o_jal_addr_valid	(),
	
	.o_j_addr		(),
	.o_j_addr_valid		(),

	.o_write_req		(),
	.o_read_req		(),
	
	.o_type			(),
	.o_op			(),
	.o_dst			(),
	.o_src0			(),
	.o_src1			(),
	.o_minor_imm		(),
	
	.rst			(rst),
	.clk			(clk)
	);


endmodule

decoder/main.vcd
$date
	Sun Mar 17 19:56:17 2019
$end
$version
	Icarus Verilog
$end
$timescale
	1ns
$end
$scope module main $end
$var reg 1 ! clk $end
$var reg 32 " inst [31:0] $end
$var reg 1 # rst $end
$var reg 1 $ valid $end
$scope module uDecoder $end
$var wire 1 % clk $end
$var wire 32 & i_inst [31:0] $end
$var wire 1 ' i_inst_valid $end
$var wire 5 ( o_dst [4:0] $end
$var wire 32 ) o_j_addr [31:0] $end
$var wire 1 * o_j_addr_valid $end
$var wire 32 + o_jal_addr [31:0] $end
$var wire 1 , o_jal_addr_valid $end
$var wire 1 - o_jr $end
$var wire 16 . o_minor_imm [15:0] $end
$var wire 4 / o_op [3:0] $end
$var wire 1 0 o_read_req $end
$var wire 5 1 o_src0 [4:0] $end
$var wire 5 2 o_src1 [4:0] $end
$var wire 2 3 o_type [1:0] $end
$var wire 1 4 o_write_req $end
$var wire 1 5 rst $end
$var wire 26 6 w_major_imm [25:0] $end
$var wire 5 7 w_src1 [4:0] $end
$upscope $end
$upscope $end
$enddefinitions $end
#0
$dumpvars
b11 7
b1000100001100000000000 6
15
04
b0 3
b11 2
b10 1
00
b0 /
b1100000000000 .
0-
0,
b1000100001100000000000 +
0*
b1000100001100000000000 )
b1 (
1'
b1000100001100000000000 &
0%
1$
1#
b1000100001100000000000 "
0!
$end
#500
1!
1%
#1000
0!
0%
#1500
1!
1%
#2000
0!
0%
#2500
1!
1%
#3000
0!
0%
#3500
1!
1%
#4000
0!
0%
0#
05
#4500
1!
1%
#5000
0!
0%
#5500
1!
1%
#6000
0!
0%
#6500
1!
1%
#7000
0!
0%
#7500
1!
1%
#8000
0!
0%
#8500
1!
1%
#9000
0!
0%
#9500
1!
1%
#10000
b10 /
b1000001000100001100000000000 "
b1000001000100001100000000000 &
0!
0%
#10500
1!
1%
#11000
0!
0%
#11500
1!
1%
#12000
0!
0%
#12500
1!
1%
#13000
0!
0%
#13500
1!
1%
#14000
0!
0%
#14500
1!
1%
#15000
0!
0%
#15500
1!
1%
#16000
0!
0%
#16500
1!
1%
#17000
0!
0%
#17500
1!
1%
#18000
0!
0%
#18500
1!
1%
#19000
0!
0%
#19500
1!
1%
#20000
b100 /
b10000001000100001100000000000 "
b10000001000100001100000000000 &
0!
0%
#20500
1!
1%
#21000
0!
0%
#21500
1!
1%
#22000
0!
0%
#22500
1!
1%
#23000
0!
0%
#23500
1!
1%
#24000
0!
0%
#24500
1!
1%
#25000
0!
0%
#25500
1!
1%
#26000
0!
0%
#26500
1!
1%
#27000
0!
0%
#27500
1!
1%
#28000
0!
0%
#28500
1!
1%
#29000
0!
0%
#29500
1!
1%
#30000
b110 /
b11000001000100001100000000000 "
b11000001000100001100000000000 &
0!
0%
#30500
1!
1%
#31000
0!
0%
#31500
1!
1%
#32000
0!
0%
#32500
1!
1%
#33000
0!
0%
#33500
1!
1%
#34000
0!
0%
#34500
1!
1%
#35000
0!
0%
#35500
1!
1%
#36000
0!
0%
#36500
1!
1%
#37000
0!
0%
#37500
1!
1%
#38000
0!
0%
#38500
1!
1%
#39000
0!
0%
#39500
1!
1%
#40000
b1000 /
b100000001000100001100000000000 "
b100000001000100001100000000000 &
0!
0%
#40500
1!
1%
#41000
0!
0%
#41500
1!
1%
#42000
0!
0%
#42500
1!
1%
#43000
0!
0%
#43500
1!
1%
#44000
0!
0%
#44500
1!
1%
#45000
0!
0%
#45500
1!
1%
#46000
0!
0%
#46500
1!
1%
#47000
0!
0%
#47500
1!
1%
#48000
0!
0%
#48500
1!
1%
#49000
0!
0%
#49500
1!
1%
#50000
b1010 /
b101000001000100001100000000000 "
b101000001000100001100000000000 &
0!
0%
#50500
1!
1%
#51000
0!
0%
#51500
1!
1%
#52000
0!
0%
#52500
1!
1%
#53000
0!
0%
#53500
1!
1%
#54000
0!
0%
#54500
1!
1%
#55000
0!
0%
#55500
1!
1%
#56000
0!
0%
#56500
1!
1%
#57000
0!
0%
#57500
1!
1%
#58000
0!
0%
#58500
1!
1%
#59000
0!
0%
#59500
1!
1%
#60000
b1100 /
b110000001000100001100000000000 "
b110000001000100001100000000000 &
0!
0%
#60500
1!
1%
#61000
0!
0%
#61500
1!
1%
#62000
0!
0%
#62500
1!
1%
#63000
0!
0%
#63500
1!
1%
#64000
0!
0%
#64500
1!
1%
#65000
0!
0%
#65500
1!
1%
#66000
0!
0%
#66500
1!
1%
#67000
0!
0%
#67500
1!
1%
#68000
0!
0%
#68500
1!
1%
#69000
0!
0%
#69500
1!
1%
#70000
b1110 /
b111000001000100001100000000000 "
b111000001000100001100000000000 &
0!
0%
#70500
1!
1%
#71000
0!
0%
#71500
1!
1%
#72000
0!
0%
#72500
1!
1%
#73000
0!
0%
#73500
1!
1%
#74000
0!
0%
#74500
1!
1%
#75000
0!
0%
#75500
1!
1%
#76000
0!
0%
#76500
1!
1%
#77000
0!
0%
#77500
1!
1%
#78000
0!
0%
#78500
1!
1%
#79000
0!
0%
#79500
1!
1%
#80000
b1 3
b0 /
b1000000001000100001100000000000 "
b1000000001000100001100000000000 &
0!
0%
#80500
1!
1%
#81000
0!
0%
#81500
1!
1%
#82000
0!
0%
#82500
1!
1%
#83000
0!
0%
#83500
1!
1%
#84000
0!
0%
#84500
1!
1%
#85000
0!
0%
#85500
1!
1%
#86000
0!
0%
#86500
1!
1%
#87000
0!
0%
#87500
1!
1%
#88000
0!
0%
#88500
1!
1%
#89000
0!
0%
#89500
1!
1%
#90000
b1 /
b1000100001000100001100000000000 "
b1000100001000100001100000000000 &
0!
0%
#90500
1!
1%
#91000
0!
0%
#91500
1!
1%
#92000
0!
0%
#92500
1!
1%
#93000
0!
0%
#93500
1!
1%
#94000
0!
0%
#94500
1!
1%
#95000
0!
0%
#95500
1!
1%
#96000
0!
0%
#96500
1!
1%
#97000
0!
0%
#97500
1!
1%
#98000
0!
0%
#98500
1!
1%
#99000
0!
0%
#99500
1!
1%
#100000
b10 /
b1001000001000100001100000000000 "
b1001000001000100001100000000000 &
0!
0%
#100500
1!
1%
#101000
0!
0%
#101500
1!
1%
#102000
0!
0%
#102500
1!
1%
#103000
0!
0%
#103500
1!
1%
#104000
0!
0%
#104500
1!
1%
#105000
0!
0%
#105500
1!
1%
#106000
0!
0%
#106500
1!
1%
#107000
0!
0%
#107500
1!
1%
#108000
0!
0%
#108500
1!
1%
#109000
0!
0%
#109500
1!
1%
#110000
b11 /
b1001100001000100001100000000000 "
b1001100001000100001100000000000 &
0!
0%
#110500
1!
1%
#111000
0!
0%
#111500
1!
1%
#112000
0!
0%
#112500
1!
1%
#113000
0!
0%
#113500
1!
1%
#114000
0!
0%
#114500
1!
1%
#115000
0!
0%
#115500
1!
1%
#116000
0!
0%
#116500
1!
1%
#117000
0!
0%
#117500
1!
1%
#118000
0!
0%
#118500
1!
1%
#119000
0!
0%
#119500
1!
1%
#120000
b100 /
b1010000001000100001100000000000 "
b1010000001000100001100000000000 &
0!
0%
#120500
1!
1%
#121000
0!
0%
#121500
1!
1%
#122000
0!
0%
#122500
1!
1%
#123000
0!
0%
#123500
1!
1%
#124000
0!
0%
#124500
1!
1%
#125000
0!
0%
#125500
1!
1%
#126000
0!
0%
#126500
1!
1%
#127000
0!
0%
#127500
1!
1%
#128000
0!
0%
#128500
1!
1%
#129000
0!
0%
#129500
1!
1%
#130000
b101 /
b1010100001000100001100000000000 "
b1010100001000100001100000000000 &
0!
0%
#130500
1!
1%
#131000
0!
0%
#131500
1!
1%
#132000
0!
0%
#132500
1!
1%
#133000
0!
0%
#133500
1!
1%
#134000
0!
0%
#134500
1!
1%
#135000
0!
0%
#135500
1!
1%
#136000
0!
0%
#136500
1!
1%
#137000
0!
0%
#137500
1!
1%
#138000
0!
0%
#138500
1!
1%
#139000
0!
0%
#139500
1!
1%
#140000
b110 /
b1011000001000100001100000000000 "
b1011000001000100001100000000000 &
0!
0%
#140500
1!
1%
#141000
0!
0%
#141500
1!
1%
#142000
0!
0%
#142500
1!
1%
#143000
0!
0%
#143500
1!
1%
#144000
0!
0%
#144500
1!
1%
#145000
0!
0%
#145500
1!
1%
#146000
0!
0%
#146500
1!
1%
#147000
0!
0%
#147500
1!
1%
#148000
0!
0%
#148500
1!
1%
#149000
0!
0%
#149500
1!
1%
#150000
1-
b0 2
b111 /
b0 (
b1 1
b0 7
b0 .
b10000000000000000 )
b10000000000000000 +
b10000000000000000 6
b1011100000000010000000000000000 "
b1011100000000010000000000000000 &
0!
0%
#150500
1!
1%
#151000
0!
0%
#151500
1!
1%
#152000
0!
0%
#152500
1!
1%
#153000
0!
0%
#153500
1!
1%
#154000
0!
0%
#154500
1!
1%
#155000
0!
0%
#155500
1!
1%
#156000
0!
0%
#156500
1!
1%
#157000
0!
0%
#157500
1!
1%
#158000
0!
0%
#158500
1!
1%
#159000
0!
0%
#159500
1!
1%
#160000
0-
b10 3
b0 /
b1 (
b10 1
b11 .
b1000100000000000000011 )
b1000100000000000000011 +
b1000100000000000000011 6
b10000000001000100000000000000011 "
b10000000001000100000000000000011 &
0!
0%
#160500
1!
1%
#161000
0!
0%
#161500
1!
1%
#162000
0!
0%
#162500
1!
1%
#163000
0!
0%
#163500
1!
1%
#164000
0!
0%
#164500
1!
1%
#165000
0!
0%
#165500
1!
1%
#166000
0!
0%
#166500
1!
1%
#167000
0!
0%
#167500
1!
1%
#168000
0!
0%
#168500
1!
1%
#169000
0!
0%
#169500
1!
1%
#170000
b10 /
b10001000001000100000000000000011 "
b10001000001000100000000000000011 &
0!
0%
#170500
1!
1%
#171000
0!
0%
#171500
1!
1%
#172000
0!
0%
#172500
1!
1%
#173000
0!
0%
#173500
1!
1%
#174000
0!
0%
#174500
1!
1%
#175000
0!
0%
#175500
1!
1%
#176000
0!
0%
#176500
1!
1%
#177000
0!
0%
#177500
1!
1%
#178000
0!
0%
#178500
1!
1%
#179000
0!
0%
#179500
1!
1%
#180000
b100 /
b10010000001000100000000000000011 "
b10010000001000100000000000000011 &
0!
0%
#180500
1!
1%
#181000
0!
0%
#181500
1!
1%
#182000
0!
0%
#182500
1!
1%
#183000
0!
0%
#183500
1!
1%
#184000
0!
0%
#184500
1!
1%
#185000
0!
0%
#185500
1!
1%
#186000
0!
0%
#186500
1!
1%
#187000
0!
0%
#187500
1!
1%
#188000
0!
0%
#188500
1!
1%
#189000
0!
0%
#189500
1!
1%
#190000
b110 /
b10011000001000100000000000000011 "
b10011000001000100000000000000011 &
0!
0%
#190500
1!
1%
#191000
0!
0%
#191500
1!
1%
#192000
0!
0%
#192500
1!
1%
#193000
0!
0%
#193500
1!
1%
#194000
0!
0%
#194500
1!
1%
#195000
0!
0%
#195500
1!
1%
#196000
0!
0%
#196500
1!
1%
#197000
0!
0%
#197500
1!
1%
#198000
0!
0%
#198500
1!
1%
#199000
0!
0%
#199500
1!
1%
#200000
10
b1000 /
b10100000001000100000000000000011 "
b10100000001000100000000000000011 &
0!
0%
#200500
1!
1%
#201000
0!
0%
#201500
1!
1%
#202000
0!
0%
#202500
1!
1%
#203000
0!
0%
#203500
1!
1%
#204000
0!
0%
#204500
1!
1%
#205000
0!
0%
#205500
1!
1%
#206000
0!
0%
#206500
1!
1%
#207000
0!
0%
#207500
1!
1%
#208000
0!
0%
#208500
1!
1%
#209000
0!
0%
#209500
1!
1%
#210000
b1 2
00
14
b1001 /
b10100100001000100000000000000011 "
b10100100001000100000000000000011 &
0!
0%
#210500
1!
1%
#211000
0!
0%
#211500
1!
1%
#212000
0!
0%
#212500
1!
1%
#213000
0!
0%
#213500
1!
1%
#214000
0!
0%
#214500
1!
1%
#215000
0!
0%
#215500
1!
1%
#216000
0!
0%
#216500
1!
1%
#217000
0!
0%
#217500
1!
1%
#218000
0!
0%
#218500
1!
1%
#219000
0!
0%
#219500
1!
1%
#220000
b0 2
04
b1010 /
b10101000001000100000000000000011 "
b10101000001000100000000000000011 &
0!
0%
#220500
1!
1%
#221000
0!
0%
#221500
1!
1%
#222000
0!
0%
#222500
1!
1%
#223000
0!
0%
#223500
1!
1%
#224000
0!
0%
#224500
1!
1%
#225000
0!
0%
#225500
1!
1%
#226000
0!
0%
#226500
1!
1%
#227000
0!
0%
#227500
1!
1%
#228000
0!
0%
#228500
1!
1%
#229000
0!
0%
#229500
1!
1%
#230000
b1011 /
b10101100001000100000000000000011 "
b10101100001000100000000000000011 &
0!
0%
#230500
1!
1%
#231000
0!
0%
#231500
1!
1%
#232000
0!
0%
#232500
1!
1%
#233000
0!
0%
#233500
1!
1%
#234000
0!
0%
#234500
1!
1%
#235000
0!
0%
#235500
1!
1%
#236000
0!
0%
#236500
1!
1%
#237000
0!
0%
#237500
1!
1%
#238000
0!
0%
#238500
1!
1%
#239000
0!
0%
#239500
1!
1%
#240000
b1100 /
b10110000001000100000000000000011 "
b10110000001000100000000000000011 &
0!
0%
#240500
1!
1%
#241000
0!
0%
#241500
1!
1%
#242000
0!
0%
#242500
1!
1%
#243000
0!
0%
#243500
1!
1%
#244000
0!
0%
#244500
1!
1%
#245000
0!
0%
#245500
1!
1%
#246000
0!
0%
#246500
1!
1%
#247000
0!
0%
#247500
1!
1%
#248000
0!
0%
#248500
1!
1%
#249000
0!
0%
#249500
1!
1%
#250000
b1101 /
b10110100001000100000000000000011 "
b10110100001000100000000000000011 &
0!
0%
#250500
1!
1%
#251000
0!
0%
#251500
1!
1%
#252000
0!
0%
#252500
1!
1%
#253000
0!
0%
#253500
1!
1%
#254000
0!
0%
#254500
1!
1%
#255000
0!
0%
#255500
1!
1%
#256000
0!
0%
#256500
1!
1%
#257000
0!
0%
#257500
1!
1%
#258000
0!
0%
#258500
1!
1%
#259000
0!
0%
#259500
1!
1%
#260000
b1110 /
b10111000001000100000000000000011 "
b10111000001000100000000000000011 &
0!
0%
#260500
1!
1%
#261000
0!
0%
#261500
1!
1%
#262000
0!
0%
#262500
1!
1%
#263000
0!
0%
#263500
1!
1%
#264000
0!
0%
#264500
1!
1%
#265000
0!
0%
#265500
1!
1%
#266000
0!
0%
#266500
1!
1%
#267000
0!
0%
#267500
1!
1%
#268000
0!
0%
#268500
1!
1%
#269000
0!
0%
#269500
1!
1%
#270000
b1111 /
b10111100001000100000000000000011 "
b10111100001000100000000000000011 &
0!
0%
#270500
1!
1%
#271000
0!
0%
#271500
1!
1%
#272000
0!
0%
#272500
1!
1%
#273000
0!
0%
#273500
1!
1%
#274000
0!
0%
#274500
1!
1%
#275000
0!
0%
#275500
1!
1%
#276000
0!
0%
#276500
1!
1%
#277000
0!
0%
#277500
1!
1%
#278000
0!
0%
#278500
1!
1%
#279000
0!
0%
#279500
1!
1%
#280000
1*
b11 3
b0 /
b0 (
b0 1
b100 .
b100 )
b100 +
b100 6
b11000000000000000000000000000100 "
b11000000000000000000000000000100 &
0!
0%
#280500
1!
1%
#281000
0!
0%
#281500
1!
1%
#282000
0!
0%
#282500
1!
1%
#283000
0!
0%
#283500
1!
1%
#284000
0!
0%
#284500
1!
1%
#285000
0!
0%
#285500
1!
1%
#286000
0!
0%
#286500
1!
1%
#287000
0!
0%
#287500
1!
1%
#288000
0!
0%
#288500
1!
1%
#289000
0!
0%
#289500
1!
1%
#290000
0*
1,
b1 /
b11000100000000000000000000000100 "
b11000100000000000000000000000100 &
0!
0%
