fifo/mFifo.v
///////////////////////////////////////////
// This modules is in modakio cpu.
// mArb.v module ver 1.0
// 2019/03/16 writen by denchu
//
`ifndef	_mFIFO_
`define	_mFIFO_
`include "./define.v"

module mFifo #(
	parameter	p_st_bits		= 32,
	parameter	p_fifo_length 		= 8,
	parameter	p_fifo_length_log2 	= 3
//	parameter	p_fifo_length_log2 	= log2(p_fifo_length)
)(
	input	[p_st_bits-1:0]	i_snk_data,
	input			i_snk_valid,
	output			o_snk_ready,
	
	output	[p_st_bits-1:0]	o_src_data,
	output			o_src_valid,
	input			i_src_ready,

	input			clk,
	input			rst

);
	//function integer log2;
        //input integer num;
        //	begin
        //		num = num - 1;
        //	for (log2 = 0; num > 0; log2 = log2 + 1)
        //		num = num >> 1;
        //	end
        //endfunction

	//reg	[p_fifo_length-1:0] 		mem [p_st_bits-1:0];
	reg	[p_st_bits-1:0] 		mem [p_fifo_length-1:0];
	reg	[p_fifo_length_log2-1:0]	w_ptr;
	reg	[p_fifo_length_log2-1:0]	r_ptr;

	// write pointer
	//always @(posedge clk or posedge rst)
	always @(posedge clk)
	begin
		if(rst) begin
			w_ptr <= 0;
		end else if (!w_full && i_snk_valid) begin
			w_ptr <= w_ptr + 1;
		end
	end
	
	// read pointer
	//always @(posedge clk or posedge rst)
	always @(posedge clk)
	begin
		if(rst) begin
			r_ptr <= 0;
		end else if (!w_empty && i_src_ready) begin
			r_ptr <= r_ptr + 1;
		end
	end

	//write buffer
	always @(posedge clk)
	begin
		if (!w_full && i_snk_valid) begin
			mem[w_ptr] <= i_snk_data;
		end
	end
	
	//read buffe
	assign o_src_data = mem[r_ptr];

	wire	w_full;
	assign 	w_full = ((w_ptr + 1 == r_ptr)||((r_ptr == 0) && (w_ptr == p_fifo_length - 1))) ? 1 : 0;
	assign	o_snk_ready = !w_full;

	wire	w_empty;
	assign 	w_empty = (w_ptr == r_ptr)? 1 : 0;
	assign	o_src_valid = !w_empty;
	
	
	
endmodule

`endif

define.v
////////////////////////////////
// modakio cpu operation number
// operation number

// func log2
//function integer log2;
//	input integer in;
//	begin
//		in = in - 1;
//		for (log2 = 0; in > 0; log2 = log2+1)
//			in = in >> 1;
//	end
//endfunction



// 
// CalcReg(CR)
// 
`define TYPE_CR		0
// interger
`define	OP_IADD		0
`define	OP_UIADD	1
`define	OP_ISUB		2
`define	OP_UISUB	3
`define	OP_IMUL		4
`define	OP_UIMUL	5
`define	OP_IDEV		6
`define	OP_UIDEV	7

//floating point 
`define	OP_FADD		8
`define	OP_FCMP		9
`define	OP_FSUB		10
`define	OP_CR_NOUSE11	11
`define	OP_FMUL		12
`define	OP_CR_NOUSE13	13
`define	OP_FDEV		14
`define	OP_CR_NOUSE15	15

// 
// LogicReg(LR)
// 
`define TYPE_LR		1

// bit logical

`define	OP_AND		0
`define	OP_OR		1
`define	OP_XOR		2
`define	OP_UCMP		3
`define	OP_LSFT		4
`define	OP_RSFT		5
`define	OP_CMP		6
`define	OP_JR		7

`define	OP_LR_NOUSE8	8
`define	OP_LR_NOUSE9	9
`define	OP_LR_NOUSE10	10
`define	OP_LR_NOUSE11	11
`define	OP_LR_NOUSE12	12
`define	OP_LR_NOUSE13	13
`define	OP_LR_NOUSE14	14
`define	OP_LR_NOUSE15	15


// 
// Immediate
// 
`define TYPE_I		2

`define	OP_IADDI	0
`define	OP_UIADDI	1
`define	OP_ISUBI	2
`define	OP_UISUBI	3
`define	OP_IMULI	4
`define	OP_UIMULI	5
`define	OP_IDEVI	6
`define	OP_UIDEVI	7

`define	OP_LW		8
`define	OP_ST		9
`define	OP_LSFTI	10
`define	OP_RSFTI	11
`define	OP_BE		12
`define	OP_BNE		13
`define	OP_CMPI		14
`define	OP_UCMPI	15


// 
// Jump
// 
`define TYPE_J		3

`define	OP_J		0
`define	OP_JAL		1
`define	OP_J_NOUSE2	2
`define	OP_J_NOUSE3	3
`define	OP_J_NOUSE4	4
`define	OP_J_NOUSE5	5
`define	OP_J_NOUSE6	6
`define	OP_J_NOUSE7	7

`define	OP_J_NOUSE8	8
`define	OP_J_NOUSE9	9
`define	OP_J_NOUSE10	10
`define	OP_J_NOUSE11	11
`define	OP_J_NOUSE12	12
`define	OP_J_NOUSE13	13
`define	OP_J_NOUSE14	14
`define	OP_J_NOUSE15	15

`define	NUM_OF_OP	42

//
// HARDWARE DISCRIPTION
//
`define	NUM_OF_FETCH_INST	4
`define	INST_FIFO_LENGTH	`NUM_OF_FETCH_INST * 2

`define WORD_BITS	32
`define	NUM_OF_REG	32
`define REG_ADDR_BITS	5 
`define MEM_ADDR_BITS	18

`define BITS_PER_BYTE	8

`define INST_BITS	`WORD_BITS
`define TYPE_BITS	2
`define OP_BITS		4
`define DST_BITS	5
`define SRC0_BITS	5
`define SRC1_BITS	5
`define MINOR_IMM_BITS	16
`define MAJOR_IMM_BITS	26

`define TYPE_OFFSET	`INST_BITS - `TYPE_BITS
`define OP_OFFSET	`INST_BITS - `TYPE_BITS - `OP_BITS
`define DST_OFFSET	`INST_BITS - `TYPE_BITS - `OP_BITS - `DST_BITS
`define SRC0_OFFSET	`INST_BITS - `TYPE_BITS - `OP_BITS - `DST_BITS - `SRC0_BITS
`define SRC1_OFFSET	`INST_BITS - `TYPE_BITS - `OP_BITS - `DST_BITS - `SRC0_BITS - `SRC1_BITS
`define MINOR_IMM_OFFSET	`INST_BITS - `TYPE_BITS - `OP_BITS - `DST_BITS - `SRC0_BITS - `MINOR_IMM_BITS
`define MAJOR_IMM_OFFSET	`INST_BITS - `TYPE_BITS - `OP_BITS - `MAJOR_IMM_BITS

`define BURST_LENGTH	4

onehot_sender/mOnehot_sender.v
///////////////////////////////////////////
// This modules is in modakio cpu.
// mOnehot_sender module ver 1.0
// 2019/03/23 writen by denchu
//
`ifndef	_mONEHOT_SENDER_
`define	_mONEHOT_SENDER_
`include "./define.v"

module mOnehot_sender (
	input				in,
	output				out,
	
	input				clk,
	input				rst
);

	reg	one_clock_before;

	// write pointer
	always @(posedge clk)
	begin
		if(rst) begin
			one_clock_before <= 0;
		end else begin
			one_clock_before <= in;
		end
	end

	assign out = (in == 1'b1 && one_clock_before == 1'b0)? 1'b1 : 1'b0;
	
endmodule

`endif

onehot_sender/main.v
`timescale  1ps/1ps

`include "../define.v"
`include "../lib/mFifo.v"
`define WORD_BITS 32

module main;
	reg rst;
	reg clk;
	reg [`INST_BITS-1:0]	data;
	reg valid;


	parameter CYCLE = 1000; //clock rate = 1000ns(1MHz)


	//reset
	initial begin
		//#(CYCLE*0.1)
				rst <= 1;
		#(CYCLE*4)	rst <= 0;
	end

	//clock
	initial begin
		clk <= 0;
	end
	always begin
		#(CYCLE/2) clk <= ~clk;
	end
	
	//count up
	initial begin
		data <= 0;
	end
	always @(posedge clk) begin
		//#(CYCLE*0.1)
			data <= data + 1;
	end
	
	//random
	initial begin
		valid <= 0;
	end
	always @(posedge clk) begin
		//#(CYCLE*0.1)
		valid <= $random % 2;
	end


	integer idx;
	initial begin
		$dumpfile("main.vcd");
		$dumpvars(0, main);
//		for(idx = 0; idx < 8; idx = idx + 1) $dumpvars(1, main.uFifo.mem[idx]);
		
		#(CYCLE*400);
//			$display(main.uFifo.w_full);
		$finish;
		
	end
	
mOnehot_sender uOnehot_sender (
	.in	(valid),
	.out	(),

	.clk	(clk),
	.rst	(rst)

);


endmodule

onehot_sender/main.vcd
$date
	Sat Mar 23 23:43:57 2019
$end
$version
	Icarus Verilog
$end
$timescale
	1ps
$end
$scope module main $end
$var reg 1 ! clk $end
$var reg 32 " data [31:0] $end
$var reg 1 # rst $end
$var reg 1 $ valid $end
$scope module uOnehot_sender $end
$var wire 1 % clk $end
$var wire 1 & in $end
$var wire 1 ' out $end
$var wire 1 ( rst $end
$var reg 1 ) one_clock_before $end
$upscope $end
$upscope $end
$enddefinitions $end
#0
$dumpvars
x)
1(
0'
0&
0%
0$
1#
b0 "
0!
$end
#500
0)
b1 "
1!
1%
#1000
0!
0%
#1500
1'
1$
1&
b10 "
1!
1%
#2000
0!
0%
#2500
b11 "
1!
1%
#3000
0!
0%
#3500
b100 "
1!
1%
#4000
0!
0%
0#
0(
#4500
0'
1)
b101 "
1!
1%
#5000
0!
0%
#5500
b110 "
1!
1%
#6000
0!
0%
#6500
b111 "
1!
1%
#7000
0!
0%
#7500
0$
0&
b1000 "
1!
1%
#8000
0!
0%
#8500
1'
0)
b1001 "
1$
1&
1!
1%
#9000
0!
0%
#9500
0'
b1010 "
1)
1!
1%
#10000
0!
0%
#10500
b1011 "
0$
0&
1!
1%
#11000
0!
0%
#11500
1'
1$
1&
b1100 "
0)
1!
1%
#12000
0!
0%
#12500
0'
1)
b1101 "
1!
1%
#13000
0!
0%
#13500
0$
0&
b1110 "
1!
1%
#14000
0!
0%
#14500
1'
0)
b1111 "
1$
1&
1!
1%
#15000
0!
0%
#15500
0'
0$
0&
b10000 "
1)
1!
1%
#16000
0!
0%
#16500
1'
0)
b10001 "
1$
1&
1!
1%
#17000
0!
0%
#17500
0'
0$
0&
b10010 "
1)
1!
1%
#18000
0!
0%
#18500
1'
0)
b10011 "
1$
1&
1!
1%
#19000
0!
0%
#19500
0'
b10100 "
1)
1!
1%
#20000
0!
0%
#20500
b10101 "
0$
0&
1!
1%
#21000
0!
0%
#21500
1'
1$
1&
b10110 "
0)
1!
1%
#22000
0!
0%
#22500
0'
1)
b10111 "
0$
0&
1!
1%
#23000
0!
0%
#23500
b11000 "
0)
1!
1%
#24000
0!
0%
#24500
b11001 "
1!
1%
#25000
0!
0%
#25500
1'
1$
1&
b11010 "
1!
1%
#26000
0!
0%
#26500
0'
1)
b11011 "
0$
0&
1!
1%
#27000
0!
0%
#27500
1'
1$
1&
b11100 "
0)
1!
1%
#28000
0!
0%
#28500
0'
1)
b11101 "
1!
1%
#29000
0!
0%
#29500
b11110 "
1!
1%
#30000
0!
0%
#30500
b11111 "
1!
1%
#31000
0!
0%
#31500
0$
0&
b100000 "
1!
1%
#32000
0!
0%
#32500
0)
b100001 "
1!
1%
#33000
0!
0%
#33500
b100010 "
1!
1%
#34000
0!
0%
#34500
b100011 "
1!
1%
#35000
0!
0%
#35500
1'
1$
1&
b100100 "
1!
1%
#36000
0!
0%
#36500
0'
1)
b100101 "
0$
0&
1!
1%
#37000
0!
0%
#37500
1'
1$
1&
b100110 "
0)
1!
1%
#38000
0!
0%
#38500
0'
1)
b100111 "
1!
1%
#39000
0!
0%
#39500
b101000 "
1!
1%
#40000
0!
0%
#40500
b101001 "
1!
1%
#41000
0!
0%
#41500
b101010 "
1!
1%
#42000
0!
0%
#42500
b101011 "
0$
0&
1!
1%
#43000
0!
0%
#43500
b101100 "
0)
1!
1%
#44000
0!
0%
#44500
1'
b101101 "
1$
1&
1!
1%
#45000
0!
0%
#45500
0'
b101110 "
1)
1!
1%
#46000
0!
0%
#46500
b101111 "
1!
1%
#47000
0!
0%
#47500
0$
0&
b110000 "
1!
1%
#48000
0!
0%
#48500
0)
b110001 "
1!
1%
#49000
0!
0%
#49500
b110010 "
1!
1%
#50000
0!
0%
#50500
b110011 "
1!
1%
#51000
0!
0%
#51500
b110100 "
1!
1%
#52000
0!
0%
#52500
1'
b110101 "
1$
1&
1!
1%
#53000
0!
0%
#53500
0'
0$
0&
b110110 "
1)
1!
1%
#54000
0!
0%
#54500
0)
b110111 "
1!
1%
#55000
0!
0%
#55500
1'
1$
1&
b111000 "
1!
1%
#56000
0!
0%
#56500
0'
1)
b111001 "
1!
1%
#57000
0!
0%
#57500
0$
0&
b111010 "
1!
1%
#58000
0!
0%
#58500
0)
b111011 "
1!
1%
#59000
0!
0%
#59500
b111100 "
1!
1%
#60000
0!
0%
#60500
b111101 "
1!
1%
#61000
0!
0%
#61500
b111110 "
1!
1%
#62000
0!
0%
#62500
1'
b111111 "
1$
1&
1!
1%
#63000
0!
0%
#63500
0'
b1000000 "
1)
1!
1%
#64000
0!
0%
#64500
b1000001 "
1!
1%
#65000
0!
0%
#65500
b1000010 "
1!
1%
#66000
0!
0%
#66500
b1000011 "
1!
1%
#67000
0!
0%
#67500
0$
0&
b1000100 "
1!
1%
#68000
0!
0%
#68500
0)
b1000101 "
1!
1%
#69000
0!
0%
#69500
1'
1$
1&
b1000110 "
1!
1%
#70000
0!
0%
#70500
0'
1)
b1000111 "
1!
1%
#71000
0!
0%
#71500
b1001000 "
1!
1%
#72000
0!
0%
#72500
b1001001 "
0$
0&
1!
1%
#73000
0!
0%
#73500
b1001010 "
0)
1!
1%
#74000
0!
0%
#74500
1'
b1001011 "
1$
1&
1!
1%
#75000
0!
0%
#75500
0'
b1001100 "
1)
1!
1%
#76000
0!
0%
#76500
b1001101 "
0$
0&
1!
1%
#77000
0!
0%
#77500
1'
1$
1&
b1001110 "
0)
1!
1%
#78000
0!
0%
#78500
0'
1)
b1001111 "
1!
1%
#79000
0!
0%
#79500
0$
0&
b1010000 "
1!
1%
#80000
0!
0%
#80500
1'
0)
b1010001 "
1$
1&
1!
1%
#81000
0!
0%
#81500
0'
b1010010 "
1)
1!
1%
#82000
0!
0%
#82500
b1010011 "
1!
1%
#83000
0!
0%
#83500
0$
0&
b1010100 "
1!
1%
#84000
0!
0%
#84500
1'
0)
b1010101 "
1$
1&
1!
1%
#85000
0!
0%
#85500
0'
b1010110 "
1)
1!
1%
#86000
0!
0%
#86500
b1010111 "
0$
0&
1!
1%
#87000
0!
0%
#87500
b1011000 "
0)
1!
1%
#88000
0!
0%
#88500
b1011001 "
1!
1%
#89000
0!
0%
#89500
b1011010 "
1!
1%
#90000
0!
0%
#90500
1'
b1011011 "
1$
1&
1!
1%
#91000
0!
0%
#91500
0'
b1011100 "
1)
1!
1%
#92000
0!
0%
#92500
b1011101 "
0$
0&
1!
1%
#93000
0!
0%
#93500
b1011110 "
0)
1!
1%
#94000
0!
0%
#94500
1'
b1011111 "
1$
1&
1!
1%
#95000
0!
0%
#95500
0'
b1100000 "
1)
1!
1%
#96000
0!
0%
#96500
b1100001 "
1!
1%
#97000
0!
0%
#97500
b1100010 "
1!
1%
#98000
0!
0%
#98500
b1100011 "
1!
1%
#99000
0!
0%
#99500
0$
0&
b1100100 "
1!
1%
#100000
0!
0%
#100500
1'
0)
b1100101 "
1$
1&
1!
1%
#101000
0!
0%
#101500
0'
b1100110 "
1)
1!
1%
#102000
0!
0%
#102500
b1100111 "
1!
1%
#103000
0!
0%
#103500
0$
0&
b1101000 "
1!
1%
#104000
0!
0%
#104500
0)
b1101001 "
1!
1%
#105000
0!
0%
#105500
b1101010 "
1!
1%
#106000
0!
0%
#106500
b1101011 "
1!
1%
#107000
0!
0%
#107500
b1101100 "
1!
1%
#108000
0!
0%
#108500
b1101101 "
1!
1%
#109000
0!
0%
#109500
b1101110 "
1!
1%
#110000
0!
0%
#110500
1'
b1101111 "
1$
1&
1!
1%
#111000
0!
0%
#111500
0'
b1110000 "
1)
1!
1%
#112000
0!
0%
#112500
b1110001 "
1!
1%
#113000
0!
0%
#113500
b1110010 "
1!
1%
#114000
0!
0%
#114500
b1110011 "
1!
1%
#115000
0!
0%
#115500
0$
0&
b1110100 "
1!
1%
#116000
0!
0%
#116500
1'
0)
b1110101 "
1$
1&
1!
1%
#117000
0!
0%
#117500
0'
b1110110 "
1)
1!
1%
#118000
0!
0%
#118500
b1110111 "
0$
0&
1!
1%
#119000
0!
0%
#119500
b1111000 "
0)
1!
1%
#120000
0!
0%
#120500
1'
b1111001 "
1$
1&
1!
1%
#121000
0!
0%
#121500
0'
b1111010 "
1)
1!
1%
#122000
0!
0%
#122500
b1111011 "
0$
0&
1!
1%
#123000
0!
0%
#123500
1'
1$
1&
b1111100 "
0)
1!
1%
#124000
0!
0%
#124500
0'
1)
b1111101 "
1!
1%
#125000
0!
0%
#125500
b1111110 "
1!
1%
#126000
0!
0%
#126500
b1111111 "
1!
1%
#127000
0!
0%
#127500
0$
0&
b10000000 "
1!
1%
#128000
0!
0%
#128500
0)
b10000001 "
1!
1%
#129000
0!
0%
#129500
b10000010 "
1!
1%
#130000
0!
0%
#130500
1'
b10000011 "
1$
1&
1!
1%
#131000
0!
0%
#131500
0'
0$
0&
b10000100 "
1)
1!
1%
#132000
0!
0%
#132500
0)
b10000101 "
1!
1%
#133000
0!
0%
#133500
b10000110 "
1!
1%
#134000
0!
0%
#134500
1'
b10000111 "
1$
1&
1!
1%
#135000
0!
0%
#135500
0'
b10001000 "
1)
1!
1%
#136000
0!
0%
#136500
b10001001 "
0$
0&
1!
1%
#137000
0!
0%
#137500
b10001010 "
0)
1!
1%
#138000
0!
0%
#138500
1'
b10001011 "
1$
1&
1!
1%
#139000
0!
0%
#139500
0'
0$
0&
b10001100 "
1)
1!
1%
#140000
0!
0%
#140500
0)
b10001101 "
1!
1%
#141000
0!
0%
#141500
b10001110 "
1!
1%
#142000
0!
0%
#142500
1'
b10001111 "
1$
1&
1!
1%
#143000
0!
0%
#143500
0'
0$
0&
b10010000 "
1)
1!
1%
#144000
0!
0%
#144500
0)
b10010001 "
1!
1%
#145000
0!
0%
#145500
1'
1$
1&
b10010010 "
1!
1%
#146000
0!
0%
#146500
0'
1)
b10010011 "
0$
0&
1!
1%
#147000
0!
0%
#147500
1'
1$
1&
b10010100 "
0)
1!
1%
#148000
0!
0%
#148500
0'
1)
b10010101 "
1!
1%
#149000
0!
0%
#149500
b10010110 "
1!
1%
#150000
0!
0%
#150500
b10010111 "
1!
1%
#151000
0!
0%
#151500
b10011000 "
1!
1%
#152000
0!
0%
#152500
b10011001 "
0$
0&
1!
1%
#153000
0!
0%
#153500
b10011010 "
0)
1!
1%
#154000
0!
0%
#154500
b10011011 "
1!
1%
#155000
0!
0%
#155500
1'
1$
1&
b10011100 "
1!
1%
#156000
0!
0%
#156500
0'
1)
b10011101 "
0$
0&
1!
1%
#157000
0!
0%
#157500
b10011110 "
0)
1!
1%
#158000
0!
0%
#158500
1'
b10011111 "
1$
1&
1!
1%
#159000
0!
0%
#159500
0'
b10100000 "
1)
1!
1%
#160000
0!
0%
#160500
b10100001 "
0$
0&
1!
1%
#161000
0!
0%
#161500
b10100010 "
0)
1!
1%
#162000
0!
0%
#162500
b10100011 "
1!
1%
#163000
0!
0%
#163500
1'
1$
1&
b10100100 "
1!
1%
#164000
0!
0%
#164500
0'
1)
b10100101 "
1!
1%
#165000
0!
0%
#165500
0$
0&
b10100110 "
1!
1%
#166000
0!
0%
#166500
0)
b10100111 "
1!
1%
#167000
0!
0%
#167500
b10101000 "
1!
1%
#168000
0!
0%
#168500
1'
b10101001 "
1$
1&
1!
1%
#169000
0!
0%
#169500
0'
b10101010 "
1)
1!
1%
#170000
0!
0%
#170500
b10101011 "
0$
0&
1!
1%
#171000
0!
0%
#171500
b10101100 "
0)
1!
1%
#172000
0!
0%
#172500
b10101101 "
1!
1%
#173000
0!
0%
#173500
1'
1$
1&
b10101110 "
1!
1%
#174000
0!
0%
#174500
0'
1)
b10101111 "
0$
0&
1!
1%
#175000
0!
0%
#175500
b10110000 "
0)
1!
1%
#176000
0!
0%
#176500
1'
b10110001 "
1$
1&
1!
1%
#177000
0!
0%
#177500
0'
0$
0&
b10110010 "
1)
1!
1%
#178000
0!
0%
#178500
0)
b10110011 "
1!
1%
#179000
0!
0%
#179500
b10110100 "
1!
1%
#180000
0!
0%
#180500
1'
b10110101 "
1$
1&
1!
1%
#181000
0!
0%
#181500
0'
0$
0&
b10110110 "
1)
1!
1%
#182000
0!
0%
#182500
1'
0)
b10110111 "
1$
1&
1!
1%
#183000
0!
0%
#183500
0'
b10111000 "
1)
1!
1%
#184000
0!
0%
#184500
b10111001 "
0$
0&
1!
1%
#185000
0!
0%
#185500
b10111010 "
0)
1!
1%
#186000
0!
0%
#186500
b10111011 "
1!
1%
#187000
0!
0%
#187500
b10111100 "
1!
1%
#188000
0!
0%
#188500
1'
b10111101 "
1$
1&
1!
1%
#189000
0!
0%
#189500
0'
0$
0&
b10111110 "
1)
1!
1%
#190000
0!
0%
#190500
0)
b10111111 "
1!
1%
#191000
0!
0%
#191500
b11000000 "
1!
1%
#192000
0!
0%
#192500
b11000001 "
1!
1%
#193000
0!
0%
#193500
1'
1$
1&
b11000010 "
1!
1%
#194000
0!
0%
#194500
0'
1)
b11000011 "
1!
1%
#195000
0!
0%
#195500
b11000100 "
1!
1%
#196000
0!
0%
#196500
b11000101 "
0$
0&
1!
1%
#197000
0!
0%
#197500
1'
1$
1&
b11000110 "
0)
1!
1%
#198000
0!
0%
#198500
0'
1)
b11000111 "
1!
1%
#199000
0!
0%
#199500
b11001000 "
1!
1%
#200000
0!
0%
#200500
b11001001 "
0$
0&
1!
1%
#201000
0!
0%
#201500
b11001010 "
0)
1!
1%
#202000
0!
0%
#202500
1'
b11001011 "
1$
1&
1!
1%
#203000
0!
0%
#203500
0'
b11001100 "
1)
1!
1%
#204000
0!
0%
#204500
b11001101 "
1!
1%
#205000
0!
0%
#205500
b11001110 "
1!
1%
#206000
0!
0%
#206500
b11001111 "
1!
1%
#207000
0!
0%
#207500
0$
0&
b11010000 "
1!
1%
#208000
0!
0%
#208500
1'
0)
b11010001 "
1$
1&
1!
1%
#209000
0!
0%
#209500
0'
b11010010 "
1)
1!
1%
#210000
0!
0%
#210500
b11010011 "
0$
0&
1!
1%
#211000
0!
0%
#211500
b11010100 "
0)
1!
1%
#212000
0!
0%
#212500
b11010101 "
1!
1%
#213000
0!
0%
#213500
b11010110 "
1!
1%
#214000
0!
0%
#214500
1'
b11010111 "
1$
1&
1!
1%
#215000
0!
0%
#215500
0'
b11011000 "
1)
1!
1%
#216000
0!
0%
#216500
b11011001 "
0$
0&
1!
1%
#217000
0!
0%
#217500
b11011010 "
0)
1!
1%
#218000
0!
0%
#218500
1'
b11011011 "
1$
1&
1!
1%
#219000
0!
0%
#219500
0'
0$
0&
b11011100 "
1)
1!
1%
#220000
0!
0%
#220500
0)
b11011101 "
1!
1%
#221000
0!
0%
#221500
1'
1$
1&
b11011110 "
1!
1%
#222000
0!
0%
#222500
0'
1)
b11011111 "
0$
0&
1!
1%
#223000
0!
0%
#223500
b11100000 "
0)
1!
1%
#224000
0!
0%
#224500
1'
b11100001 "
1$
1&
1!
1%
#225000
0!
0%
#225500
0'
0$
0&
b11100010 "
1)
1!
1%
#226000
0!
0%
#226500
0)
b11100011 "
1!
1%
#227000
0!
0%
#227500
1'
1$
1&
b11100100 "
1!
1%
#228000
0!
0%
#228500
0'
1)
b11100101 "
1!
1%
#229000
0!
0%
#229500
b11100110 "
1!
1%
#230000
0!
0%
#230500
b11100111 "
0$
0&
1!
1%
#231000
0!
0%
#231500
b11101000 "
0)
1!
1%
#232000
0!
0%
#232500
b11101001 "
1!
1%
#233000
0!
0%
#233500
1'
1$
1&
b11101010 "
1!
1%
#234000
0!
0%
#234500
0'
1)
b11101011 "
0$
0&
1!
1%
#235000
0!
0%
#235500
b11101100 "
0)
1!
1%
#236000
0!
0%
#236500
1'
b11101101 "
1$
1&
1!
1%
#237000
0!
0%
#237500
0'
0$
0&
b11101110 "
1)
1!
1%
#238000
0!
0%
#238500
0)
b11101111 "
1!
1%
#239000
0!
0%
#239500
b11110000 "
1!
1%
#240000
0!
0%
#240500
b11110001 "
1!
1%
#241000
0!
0%
#241500
1'
1$
1&
b11110010 "
1!
1%
#242000
0!
0%
#242500
0'
1)
b11110011 "
0$
0&
1!
1%
#243000
0!
0%
#243500
b11110100 "
0)
1!
1%
#244000
0!
0%
#244500
b11110101 "
1!
1%
#245000
0!
0%
#245500
1'
1$
1&
b11110110 "
1!
1%
#246000
0!
0%
#246500
0'
1)
b11110111 "
1!
1%
#247000
0!
0%
#247500
0$
0&
b11111000 "
1!
1%
#248000
0!
0%
#248500
1'
0)
b11111001 "
1$
1&
1!
1%
#249000
0!
0%
#249500
0'
b11111010 "
1)
1!
1%
#250000
0!
0%
#250500
b11111011 "
1!
1%
#251000
0!
0%
#251500
b11111100 "
1!
1%
#252000
0!
0%
#252500
b11111101 "
0$
0&
1!
1%
#253000
0!
0%
#253500
1'
1$
1&
b11111110 "
0)
1!
1%
#254000
0!
0%
#254500
0'
1)
b11111111 "
1!
1%
#255000
0!
0%
#255500
b100000000 "
1!
1%
#256000
0!
0%
#256500
b100000001 "
0$
0&
1!
1%
#257000
0!
0%
#257500
b100000010 "
0)
1!
1%
#258000
0!
0%
#258500
1'
b100000011 "
1$
1&
1!
1%
#259000
0!
0%
#259500
0'
0$
0&
b100000100 "
1)
1!
1%
#260000
0!
0%
#260500
0)
b100000101 "
1!
1%
#261000
0!
0%
#261500
1'
1$
1&
b100000110 "
1!
1%
#262000
0!
0%
#262500
0'
1)
b100000111 "
1!
1%
#263000
0!
0%
#263500
0$
0&
b100001000 "
1!
1%
#264000
0!
0%
#264500
0)
b100001001 "
1!
1%
#265000
0!
0%
#265500
1'
1$
1&
b100001010 "
1!
1%
#266000
0!
0%
#266500
0'
1)
b100001011 "
0$
0&
1!
1%
#267000
0!
0%
#267500
b100001100 "
0)
1!
1%
#268000
0!
0%
#268500
1'
b100001101 "
1$
1&
1!
1%
#269000
0!
0%
#269500
0'
0$
0&
b100001110 "
1)
1!
1%
#270000
0!
0%
#270500
1'
0)
b100001111 "
1$
1&
1!
1%
#271000
0!
0%
#271500
0'
b100010000 "
1)
1!
1%
#272000
0!
0%
#272500
b100010001 "
0$
0&
1!
1%
#273000
0!
0%
#273500
1'
1$
1&
b100010010 "
0)
1!
1%
#274000
0!
0%
#274500
0'
1)
b100010011 "
0$
0&
1!
1%
#275000
0!
0%
#275500
1'
1$
1&
b100010100 "
0)
1!
1%
#276000
0!
0%
#276500
0'
1)
b100010101 "
0$
0&
1!
1%
#277000
0!
0%
#277500
b100010110 "
0)
1!
1%
#278000
0!
0%
#278500
1'
b100010111 "
1$
1&
1!
1%
#279000
0!
0%
#279500
0'
0$
0&
b100011000 "
1)
1!
1%
#280000
0!
0%
#280500
0)
b100011001 "
1!
1%
#281000
0!
0%
#281500
b100011010 "
1!
1%
#282000
0!
0%
#282500
1'
b100011011 "
1$
1&
1!
1%
#283000
0!
0%
#283500
0'
b100011100 "
1)
1!
1%
#284000
0!
0%
#284500
b100011101 "
1!
1%
#285000
0!
0%
#285500
b100011110 "
1!
1%
#286000
0!
0%
#286500
b100011111 "
1!
1%
#287000
0!
0%
#287500
0$
0&
b100100000 "
1!
1%
#288000
0!
0%
#288500
1'
0)
b100100001 "
1$
1&
1!
1%
#289000
0!
0%
#289500
0'
b100100010 "
1)
1!
1%
#290000
0!
0%
#290500
b100100011 "
1!
1%
#291000
0!
0%
#291500
0$
0&
b100100100 "
1!
1%
#292000
0!
0%
#292500
0)
b100100101 "
1!
1%
#293000
0!
0%
#293500
b100100110 "
1!
1%
#294000
0!
0%
#294500
b100100111 "
1!
1%
#295000
0!
0%
#295500
b100101000 "
1!
1%
#296000
0!
0%
#296500
b100101001 "
1!
1%
#297000
0!
0%
#297500
1'
1$
1&
b100101010 "
1!
1%
#298000
0!
0%
#298500
0'
1)
b100101011 "
1!
1%
#299000
0!
0%
#299500
b100101100 "
1!
1%
#300000
0!
0%
#300500
b100101101 "
1!
1%
#301000
0!
0%
#301500
b100101110 "
1!
1%
#302000
0!
0%
#302500
b100101111 "
1!
1%
#303000
0!
0%
#303500
b100110000 "
1!
1%
#304000
0!
0%
#304500
b100110001 "
0$
0&
1!
1%
#305000
0!
0%
#305500
1'
1$
1&
b100110010 "
0)
1!
1%
#306000
0!
0%
#306500
0'
1)
b100110011 "
1!
1%
#307000
0!
0%
#307500
b100110100 "
1!
1%
#308000
0!
0%
#308500
b100110101 "
1!
1%
#309000
0!
0%
#309500
b100110110 "
1!
1%
#310000
0!
0%
#310500
b100110111 "
1!
1%
#311000
0!
0%
#311500
b100111000 "
1!
1%
#312000
0!
0%
#312500
b100111001 "
1!
1%
#313000
0!
0%
#313500
0$
0&
b100111010 "
1!
1%
#314000
0!
0%
#314500
0)
b100111011 "
1!
1%
#315000
0!
0%
#315500
1'
1$
1&
b100111100 "
1!
1%
#316000
0!
0%
#316500
0'
1)
b100111101 "
1!
1%
#317000
0!
0%
#317500
0$
0&
b100111110 "
1!
1%
#318000
0!
0%
#318500
0)
b100111111 "
1!
1%
#319000
0!
0%
#319500
b101000000 "
1!
1%
#320000
0!
0%
#320500
b101000001 "
1!
1%
#321000
0!
0%
#321500
1'
1$
1&
b101000010 "
1!
1%
#322000
0!
0%
#322500
0'
1)
b101000011 "
0$
0&
1!
1%
#323000
0!
0%
#323500
b101000100 "
0)
1!
1%
#324000
0!
0%
#324500
b101000101 "
1!
1%
#325000
0!
0%
#325500
b101000110 "
1!
1%
#326000
0!
0%
#326500
b101000111 "
1!
1%
#327000
0!
0%
#327500
b101001000 "
1!
1%
#328000
0!
0%
#328500
1'
b101001001 "
1$
1&
1!
1%
#329000
0!
0%
#329500
0'
0$
0&
b101001010 "
1)
1!
1%
#330000
0!
0%
#330500
0)
b101001011 "
1!
1%
#331000
0!
0%
#331500
1'
1$
1&
b101001100 "
1!
1%
#332000
0!
0%
#332500
0'
1)
b101001101 "
0$
0&
1!
1%
#333000
0!
0%
#333500
b101001110 "
0)
1!
1%
#334000
0!
0%
#334500
b101001111 "
1!
1%
#335000
0!
0%
#335500
b101010000 "
1!
1%
#336000
0!
0%
#336500
1'
b101010001 "
1$
1&
1!
1%
#337000
0!
0%
#337500
0'
b101010010 "
1)
1!
1%
#338000
0!
0%
#338500
b101010011 "
1!
1%
#339000
0!
0%
#339500
b101010100 "
1!
1%
#340000
0!
0%
#340500
b101010101 "
1!
1%
#341000
0!
0%
#341500
0$
0&
b101010110 "
1!
1%
#342000
0!
0%
#342500
1'
0)
b101010111 "
1$
1&
1!
1%
#343000
0!
0%
#343500
0'
b101011000 "
1)
1!
1%
