fifo/mFifo.v
///////////////////////////////////////////
// This modules is in modakio cpu.
// mArb.v module ver 1.0
// 2019/03/16 writen by denchu
//
`ifndef	_mFIFO_
`define	_mFIFO_
`include "./define.v"

module mFifo #(
	parameter	p_st_bits		= 32,
	parameter	p_fifo_length 		= 8,
	parameter	p_fifo_length_log2 	= 3
//	parameter	p_fifo_length_log2 	= log2(p_fifo_length)
)(
	input	[p_st_bits-1:0]	i_snk_data,
	input			i_snk_valid,
	output			o_snk_ready,
	
	output	[p_st_bits-1:0]	o_src_data,
	output			o_src_valid,
	input			i_src_ready,

	input			clk,
	input			rst

);
	//function integer log2;
        //input integer num;
        //	begin
        //		num = num - 1;
        //	for (log2 = 0; num > 0; log2 = log2 + 1)
        //		num = num >> 1;
        //	end
        //endfunction

	//reg	[p_fifo_length-1:0] 		mem [p_st_bits-1:0];
	reg	[p_st_bits-1:0] 		mem [p_fifo_length-1:0];
	reg	[p_fifo_length_log2-1:0]	w_ptr;
	reg	[p_fifo_length_log2-1:0]	r_ptr;

	// write pointer
	//always @(posedge clk or posedge rst)
	always @(posedge clk)
	begin
		if(rst) begin
			w_ptr <= 0;
		end else if (!w_full && i_snk_valid) begin
			w_ptr <= w_ptr + 1;
		end
	end
	
	// read pointer
	//always @(posedge clk or posedge rst)
	always @(posedge clk)
	begin
		if(rst) begin
			r_ptr <= 0;
		end else if (!w_empty && i_src_ready) begin
			r_ptr <= r_ptr + 1;
		end
	end

	//write buffer
	always @(posedge clk)
	begin
		if (!w_full && i_snk_valid) begin
			mem[w_ptr] <= i_snk_data;
		end
	end
	
	//read buffe
	assign o_src_data = mem[r_ptr];

	wire	w_full;
	assign 	w_full = ((w_ptr + 1 == r_ptr)||((r_ptr == 0) && (w_ptr == p_fifo_length - 1))) ? 1 : 0;
	assign	o_snk_ready = !w_full;

	wire	w_empty;
	assign 	w_empty = (w_ptr == r_ptr)? 1 : 0;
	assign	o_src_valid = !w_empty;
	
	
	
endmodule

`endif

define.v
////////////////////////////////
// modakio cpu operation number
// operation number

// func log2
//function integer log2;
//	input integer in;
//	begin
//		in = in - 1;
//		for (log2 = 0; in > 0; log2 = log2+1)
//			in = in >> 1;
//	end
//endfunction



// 
// CalcReg(CR)
// 
`define TYPE_CR		0
// interger
`define	OP_IADD		0
`define	OP_UIADD	1
`define	OP_ISUB		2
`define	OP_UISUB	3
`define	OP_IMUL		4
`define	OP_UIMUL	5
`define	OP_IDEV		6
`define	OP_UIDEV	7

//floating point 
`define	OP_FADD		8
`define	OP_FCMP		9
`define	OP_FSUB		10
`define	OP_CR_NOUSE11	11
`define	OP_FMUL		12
`define	OP_CR_NOUSE13	13
`define	OP_FDEV		14
`define	OP_CR_NOUSE15	15

// 
// LogicReg(LR)
// 
`define TYPE_LR		1

// bit logical

`define	OP_AND		0
`define	OP_OR		1
`define	OP_XOR		2
`define	OP_UCMP		3
`define	OP_LSFT		4
`define	OP_RSFT		5
`define	OP_CMP		6
`define	OP_JR		7

`define	OP_LR_NOUSE8	8
`define	OP_LR_NOUSE9	9
`define	OP_LR_NOUSE10	10
`define	OP_LR_NOUSE11	11
`define	OP_LR_NOUSE12	12
`define	OP_LR_NOUSE13	13
`define	OP_LR_NOUSE14	14
`define	OP_LR_NOUSE15	15


// 
// Immediate
// 
`define TYPE_I		2

`define	OP_IADDI	0
`define	OP_UIADDI	1
`define	OP_ISUBI	2
`define	OP_UISUBI	3
`define	OP_IMULI	4
`define	OP_UIMULI	5
`define	OP_IDEVI	6
`define	OP_UIDEVI	7

`define	OP_LW		8
`define	OP_ST		9
`define	OP_LSFTI	10
`define	OP_RSFTI	11
`define	OP_BE		12
`define	OP_BNE		13
`define	OP_CMPI		14
`define	OP_UCMPI	15


// 
// Jump
// 
`define TYPE_J		3

`define	OP_J		0
`define	OP_JAL		1
`define	OP_J_NOUSE2	2
`define	OP_J_NOUSE3	3
`define	OP_J_NOUSE4	4
`define	OP_J_NOUSE5	5
`define	OP_J_NOUSE6	6
`define	OP_J_NOUSE7	7

`define	OP_J_NOUSE8	8
`define	OP_J_NOUSE9	9
`define	OP_J_NOUSE10	10
`define	OP_J_NOUSE11	11
`define	OP_J_NOUSE12	12
`define	OP_J_NOUSE13	13
`define	OP_J_NOUSE14	14
`define	OP_J_NOUSE15	15

`define	NUM_OF_OP	42

//
// HARDWARE DISCRIPTION
//
`define	NUM_OF_FETCH_INST	4
`define	INST_FIFO_LENGTH	`NUM_OF_FETCH_INST * 2

`define WORD_BITS	32
`define	NUM_OF_REG	32
`define REG_ADDR_BITS	5 
`define MEM_ADDR_BITS	18

`define BITS_PER_BYTE	8

`define INST_BITS	`WORD_BITS
`define TYPE_BITS	2
`define OP_BITS		4
`define DST_BITS	5
`define SRC0_BITS	5
`define SRC1_BITS	5
`define MINOR_IMM_BITS	16
`define MAJOR_IMM_BITS	26

`define TYPE_OFFSET	`INST_BITS - `TYPE_BITS
`define OP_OFFSET	`INST_BITS - `TYPE_BITS - `OP_BITS
`define DST_OFFSET	`INST_BITS - `TYPE_BITS - `OP_BITS - `DST_BITS
`define SRC0_OFFSET	`INST_BITS - `TYPE_BITS - `OP_BITS - `DST_BITS - `SRC0_BITS
`define SRC1_OFFSET	`INST_BITS - `TYPE_BITS - `OP_BITS - `DST_BITS - `SRC0_BITS - `SRC1_BITS
`define MINOR_IMM_OFFSET	`INST_BITS - `TYPE_BITS - `OP_BITS - `DST_BITS - `SRC0_BITS - `MINOR_IMM_BITS
`define MAJOR_IMM_OFFSET	`INST_BITS - `TYPE_BITS - `OP_BITS - `MAJOR_IMM_BITS

`define BURST_LENGTH	4

alu/mAlu.v
///////////////////////////////////////////
// This modules is in modakio cpu.
// mALUx module ver 1.0
// 2018/05/05 writen by dtanaka
//
`ifndef _mALU_
`define _mALU_
`include "./define.v"

module mAlu (
	input	[`WORD_BITS-1:0]	i_operand_0_val,
	input	[`WORD_BITS-1:0]	i_operand_1_val,
	output	[`WORD_BITS-1:0]	o_result_val,
	output				o_result_valid,
	
	input	[`TYPE_BITS-1:0]	i_type,
	input	[`OP_BITS-1:0]		i_op,
	input				i_calc_start,

	input				clk,
	input				rst
	);

	reg	[`WORD_BITS-1:0]	r_result_val;
	reg				r_result_valid;	

	wire	[`WORD_BITS-1:0]	w_cr_result	[(1<<`OP_BITS)-1:0];
	wire	[`WORD_BITS-1:0]	w_lr_result	[(1<<`OP_BITS)-1:0];
	wire	[`WORD_BITS-1:0]	w_i_result	[(1<<`OP_BITS)-1:0];
	wire	[`WORD_BITS-1:0]	w_j_result	[(1<<`OP_BITS)-1:0];
	
	//
	// calc reg
	//

	// OP_IADD
	assign	w_cr_result[`OP_IADD]	= i_operand_0_val + i_operand_1_val;
	
	// OP_UIADD
	assign	w_cr_result[`OP_UIADD]	= i_operand_0_val + i_operand_1_val;
	
	// OP_ISUB
	assign	w_cr_result[`OP_ISUB] 	= i_operand_0_val - i_operand_1_val;
	
	// OP_UISUB
	assign	w_cr_result[`OP_UISUB] 	= i_operand_0_val - i_operand_1_val;
	
	// OP_IMUL
	assign	w_cr_result[`OP_IMUL] 	= i_operand_0_val * i_operand_1_val;
	
	// OP_UIMUL
	assign	w_cr_result[`OP_UIMUL] 	= i_operand_0_val * i_operand_1_val;
	
	// OP_IDEV
	wire	w_operand_0_minus;
	wire	w_operand_1_minus;
	assign	w_operand_0_minus = i_operand_0_val[`WORD_BITS-1];
	assign	w_operand_1_minus = i_operand_1_val[`WORD_BITS-1];

	wire	[`WORD_BITS-1:0]	w_idev_operand_0_med;
	wire	[`WORD_BITS-1:0]	w_idev_operand_1_med;
	wire	[`WORD_BITS-1:0]	w_idev_result_med;

	assign	w_idev_operand_0_med 	= (w_operand_0_minus == 1'b1)? ~i_operand_0_val + 1 : i_operand_0_val;
	assign	w_idev_operand_1_med 	= (w_operand_1_minus == 1'b1)? ~i_operand_1_val + 1 : i_operand_1_val;
	assign	w_idev_result_med	=  w_idev_operand_0_med / w_idev_operand_1_med;
	assign	w_cr_result[`OP_IDEV]	= ((w_operand_0_minus ^ w_operand_1_minus) ==1'b1) ? ~w_idev_result_med + 1 : w_idev_result_med;
	
	// OP_UIDEV
	assign	w_cr_result[`OP_UIDEV] 	= i_operand_0_val / i_operand_1_val;
	
	// OP_FADD
	assign	w_cr_result[`OP_FADD] 	= 0;
	
	// OP_FCMP
	assign	w_cr_result[`OP_FCMP] 	= 0;
	
	// OP_FSUB
	assign	w_cr_result[`OP_FSUB] 	= 0;
	
	// NO USE
	assign	w_cr_result[`OP_CR_NOUSE11] 	= 0;
	
	// OP_FMUL
	assign	w_cr_result[`OP_FMUL] 	= 0;
	
	// NO USE
	assign	w_cr_result[`OP_CR_NOUSE13] 	= 0;

	// OP_FDEV
	assign	w_cr_result[`OP_FDEV] 	= 0;
	
	// NO USE
	assign	w_cr_result[`OP_CR_NOUSE15] 	= 0;
	
	//
	// logic reg
	//
	
	// OP_AND
	assign	w_lr_result[`OP_AND] 	= i_operand_0_val & i_operand_1_val;
	
	// OP_OR
	assign	w_lr_result[`OP_OR] 	= i_operand_0_val | i_operand_1_val;
	
	// OP_XOR
	assign	w_lr_result[`OP_XOR]	= i_operand_0_val ^ i_operand_1_val;
	
	// OP_UCMP
	assign	w_lr_result[`OP_UCMP] 	= (i_operand_0_val > i_operand_1_val)? 1 : 0;
	
	// OP_LSFT
	assign	w_lr_result[`OP_LSFT] 	= i_operand_0_val << i_operand_1_val;
	
	// OP_RSFT
	assign	w_lr_result[`OP_RSFT] 	= i_operand_0_val >> i_operand_1_val;
	
	// OP_CMP
	assign	w_lr_result[`OP_CMP] 	= ((i_operand_0_val[`WORD_BITS-1] == 1'b1) && (i_operand_1_val[`WORD_BITS-1] == 1'b0))? 0 :
				  	  ((i_operand_0_val[`WORD_BITS-1] == 1'b0) && (i_operand_1_val[`WORD_BITS-1] == 1'b1))? 1 :
				          (i_operand_0_val > i_operand_1_val)? 1 : 0;
	
	// OP_JR
	assign	w_lr_result[`OP_JR] 		= 0;
	
	//OP_LR_NOUSE8	8
	assign	w_lr_result[`OP_LR_NOUSE8] 	= 0;
	
	//OP_LR_NOUSE9	9
	assign	w_lr_result[`OP_LR_NOUSE9] 	= 0;
	
	//OP_LR_NOUSE10	10
	assign	w_lr_result[`OP_LR_NOUSE10] 	= 0;
	
	//OP_LR_NOUSE11	11
	assign	w_lr_result[`OP_LR_NOUSE11] 	= 0;
	
	//OP_LR_NOUSE12	12
	assign	w_lr_result[`OP_LR_NOUSE12] 	= 0;
	
	//OP_LR_NOUSE13	13
	assign	w_lr_result[`OP_LR_NOUSE13] 	= 0;
	
	//OP_LR_NOUSE14	14
	assign	w_lr_result[`OP_LR_NOUSE14] 	= 0;
	
	//OP_LR_NOUSE15	15
	assign	w_lr_result[`OP_LR_NOUSE15] 	= 0;

	//
	// Immediate
	//
	
	// OP_IADDI
	assign	w_i_result[`OP_IADDI] 		= w_cr_result[`OP_IADD];
	
	// OP_UIADDI
	assign	w_i_result[`OP_UIADDI] 		= w_cr_result[`OP_UIADD];
	
	// OP_ISUBI
	assign	w_i_result[`OP_ISUBI] 		= w_cr_result[`OP_ISUB];
	
	// OP_UISUBI
	assign	w_i_result[`OP_UISUBI] 		= w_cr_result[`OP_UISUB];
	
	// OP_IMULI
	assign	w_i_result[`OP_IMULI] 		= w_cr_result[`OP_IMUL];
	
	// OP_UIMULI
	assign	w_i_result[`OP_UIMULI] 		= w_cr_result[`OP_UIMUL];
	
	// OP_IDEVI
	assign	w_i_result[`OP_IDEVI] 		= w_cr_result[`OP_IDEV];
	
	// OP_UIDEVI
	assign	w_i_result[`OP_UIDEVI] 		= w_cr_result[`OP_UIDEV];
	
	// OP_LW
	assign	w_i_result[`OP_LW] 		= 0;
	
	// OP_ST
	assign	w_i_result[`OP_ST] 		= 0;
	
	// OP_LSFTI
	assign	w_i_result[`OP_LSFTI] 		= w_lr_result[`OP_LSFT];
	
	// OP_RSFTI
	assign	w_i_result[`OP_RSFTI] 		= w_lr_result[`OP_RSFT];
	
	// OP_BE
	assign	w_i_result[`OP_BE] 		= 0;
	
	// OP_BNE
	assign	w_i_result[`OP_BNE] 		= 0;
	
	// OP_CMPI
	assign	w_i_result[`OP_CMPI] 		= w_lr_result[`OP_CMP];
	
	// OP_UCMPI
	assign	w_i_result[`OP_UCMPI] 		= w_lr_result[`OP_UCMP];
	

	//
	// Jump
	//
	
	// OP_J
	assign	w_j_result[`OP_J] 		= 0;
	
	// OP_JAL
	assign	w_j_result[`OP_JAL] 		= 0;

	//OP_J_NOUSE2	2
	assign	w_j_result[`OP_J_NOUSE2] 	= 0;
	
	//OP_J_NOUSE3	3
	assign	w_j_result[`OP_J_NOUSE3] 	= 0;
	
	//OP_J_NOUSE4	
	assign	w_j_result[`OP_J_NOUSE4] 	= 0;
	
	//OP_J_NOUSE5	5
	assign	w_j_result[`OP_J_NOUSE5] 	= 0;
	
	//OP_J_NOUSE6	6
	assign	w_j_result[`OP_J_NOUSE6] 	= 0;
	
	//OP_J_NOUSE7	7
	assign	w_j_result[`OP_J_NOUSE7] 	= 0;
	
	//OP_J_NOUSE8	8
	assign	w_j_result[`OP_J_NOUSE8] 	= 0;
	
	//OP_J_NOUSE9	9
	assign	w_j_result[`OP_J_NOUSE9] 	= 0;
	
	//OP_J_NOUSE10	10
	assign	w_j_result[`OP_J_NOUSE10] 	= 0;
	
	//OP_J_NOUSE11	11
	assign	w_j_result[`OP_J_NOUSE11] 	= 0;
	
	//OP_J_NOUSE12	12
	assign	w_j_result[`OP_J_NOUSE12] 	= 0;
	
	//OP_J_NOUSE13	13
	assign	w_j_result[`OP_J_NOUSE13] 	= 0;
	
	//OP_J_NOUSE14	14
	assign	w_j_result[`OP_J_NOUSE14] 	= 0;
	
	//OP_J_NOUSE15	15
	assign	w_j_result[`OP_J_NOUSE15] 	= 0;

	//
	//  Interconnect
	//

	wire	[`WORD_BITS-1:0]	w_result_val;

	assign	w_result_val = 	(i_type==`TYPE_CR)? w_cr_result[i_op] :
				(i_type==`TYPE_LR)? w_lr_result[i_op] :
				(i_type==`TYPE_I)?  w_i_result [i_op] : w_j_result [i_op];
	always@(posedge clk)
	begin
		if(rst) begin
			r_result_val <= 0;
		end else begin
			r_result_val <= w_result_val;
		end
	end
	
	always@(posedge clk)
	begin
		if(rst) begin
			r_result_valid <= 0;
		end else begin
			r_result_valid <= i_calc_start;
		end
	end

	assign	o_result_val 	= r_result_val;
	assign	o_result_valid 	= r_result_valid;

endmodule	

`endif

alu/main.v
`timescale  1ps/1ps

`include "../define.v"
`include "../lib/mFifo.v"
`define WORD_BITS 32

module main;
	reg rst;
	reg clk;
	reg [`INST_BITS-1:0]	data;
	reg [`INST_BITS-1:0]	counter;
	reg valid;


	parameter CYCLE = 1000; //clock rate = 1000ns(1MHz)


	//reset
	initial begin
		//#(CYCLE*0.1)
				rst <= 1;
		#(CYCLE*4)	rst <= 0;
	end

	//clock
	initial begin
		clk <= 0;
	end
	always begin
		#(CYCLE/2) clk <= ~clk;
	end
	
	//count up
	initial begin
		data <= 0;
	end
	always @(posedge clk) begin
		//#(CYCLE*0.1)
			data <= data + 1;
	end
	
	//random
	initial begin
		valid <= 0;
	end
	always @(posedge clk) begin
		//#(CYCLE*0.1)
		valid <= $random % 2;
	end

	reg	[3:0]	valid4;
	//random
	initial begin
		counter	<= 0;
	end
	always @(posedge clk) begin
		//#(CYCLE*0.1)
		counter <= counter + 1;
	end

	integer idx;
	initial begin
		$dumpfile("main.vcd");
		$dumpvars(0, main);
//		for(idx = 0; idx < 8; idx = idx + 1) $dumpvars(1, main.uFifo.mem[idx]);
		
		#(CYCLE*400);
//			$display(main.uFifo.w_full);
		$finish;
		
	end

	reg	[32*10-1:0]	test	[1023:0];
	reg	[31:0]	r_src0;
	reg	[31:0]	r_src1;
	reg	[31:0]	r_type;
	reg	[31:0]	r_op;
	reg	[31:0]	r_calc_start;
	reg	[31:0]	r_calc_complete;

	reg	[31:0]	r_writedata;
	reg	[31:0]	r_addr;
	reg	[31:0]	r_read;
	reg	[31:0]	r_write;
	
	initial begin 
		$readmemh("test.hex", test);
	end
	always @(posedge clk)
	begin
		if(rst) begin
			r_src0			<=0;
			r_src1			<=0;
			r_type			<=0;
			r_op			<=0;
			r_calc_start		<=0;
			r_calc_complete		<=0;
			r_writedata		<=0;
			r_addr			<=0;
			r_read			<=0;
			r_write			<=0;
		end else begin
			r_src0			<=test[counter][32*10-1:32* 9];
			r_src1			<=test[counter][32* 9-1:32* 8];
			r_type			<=test[counter][32* 8-1:32* 7];
			r_op			<=test[counter][32* 7-1:32* 6];
			r_calc_start		<=test[counter][32* 6-1:32* 5];
			r_calc_complete		<=test[counter][32* 5-1:32* 4];
			r_writedata		<=test[counter][32* 4-1:32* 3];
			r_addr			<=test[counter][32* 3-1:32* 2];
			r_read			<=test[counter][32* 2-1:32* 1];
			r_write			<=test[counter][32* 1-1:32* 0];
		end
	end

	initial begin
		$dumpfile("main.vcd");
		$dumpvars(0, main);
//		for(idx = 0; idx < 8; idx = idx + 1) $dumpvars(1, main.uFifo.mem[idx]);
		
		#(CYCLE*400);
//			$display(main.uFifo.w_full);
		$finish;
		
	end
	
	
	mAlu uAlu (
		.i_operand_0_val	(r_src0),
		.i_operand_1_val	(r_src1),
		.o_result_val		(),
		.o_result_valid		(),
		
		.i_type			(r_type),
		.i_op			(r_op),
		.i_calc_start		(r_calc_start),

		.clk			(clk),
		.rst			(rst)
	);

endmodule

alu/main.vcd
$date
	Wed May  1 02:18:44 2019
$end
$version
	Icarus Verilog
$end
$timescale
	1ps
$end
$scope module main $end
$var reg 1 ! clk $end
$var reg 32 " counter [31:0] $end
$var reg 32 # data [31:0] $end
$var reg 32 $ r_addr [31:0] $end
$var reg 32 % r_calc_complete [31:0] $end
$var reg 32 & r_calc_start [31:0] $end
$var reg 32 ' r_op [31:0] $end
$var reg 32 ( r_read [31:0] $end
$var reg 32 ) r_src0 [31:0] $end
$var reg 32 * r_src1 [31:0] $end
$var reg 32 + r_type [31:0] $end
$var reg 32 , r_write [31:0] $end
$var reg 32 - r_writedata [31:0] $end
$var reg 1 . rst $end
$var reg 1 / valid $end
$scope module uAlu $end
$var wire 1 0 clk $end
$var wire 1 1 i_calc_start $end
$var wire 4 2 i_op [3:0] $end
$var wire 32 3 i_operand_0_val [31:0] $end
$var wire 32 4 i_operand_1_val [31:0] $end
$var wire 2 5 i_type [1:0] $end
$var wire 32 6 o_result_val [31:0] $end
$var wire 1 7 o_result_valid $end
$var wire 1 8 rst $end
$var wire 32 9 w_idev_operand_0_med [31:0] $end
$var wire 32 : w_idev_operand_1_med [31:0] $end
$var wire 32 ; w_idev_result_med [31:0] $end
$var wire 1 < w_operand_0_minus $end
$var wire 1 = w_operand_1_minus $end
$var wire 32 > w_result_val [31:0] $end
$var reg 32 ? r_result_val [31:0] $end
$var reg 1 @ r_result_valid $end
$upscope $end
$upscope $end
$scope module main $end
$scope module uAlu $end
$upscope $end
$upscope $end
$enddefinitions $end
#0
$dumpvars
x@
bx ?
bx >
x=
x<
bx ;
bx :
bx 9
18
x7
bx 6
bx 5
bx 4
bx 3
bx 2
x1
00
0/
1.
bx -
bx ,
bx +
bx *
bx )
bx (
bx '
bx &
bx %
bx $
b0 #
b0 "
0!
$end
#500
b0 :
b0 9
b0 >
01
b0 2
b0 5
0=
0<
b0 ?
b0 6
0@
07
b1 #
b1 "
b0 ,
b0 (
b0 $
b0 -
b0 %
b0 &
b0 '
b0 +
b0 *
b0 4
b0 )
b0 3
1!
10
#1000
0!
00
#1500
b10 "
1/
b10 #
1!
10
#2000
0!
00
#2500
b11 #
b11 "
1!
10
#3000
0!
00
#3500
b100 "
b100 #
1!
10
#4000
0!
00
0.
08
#4500
b101 #
b101 "
1!
10
#5000
0!
00
#5500
b110 "
b110 #
1!
10
#6000
0!
00
#6500
b111 #
b111 "
1!
10
#7000
0!
00
#7500
b1000 "
0/
b1000 #
1!
10
#8000
0!
00
#8500
b1001 #
1/
b1001 "
1!
10
#9000
0!
00
#9500
b1010 "
b1010 #
1!
10
#10000
0!
00
#10500
b1011 #
0/
b1011 "
1!
10
#11000
0!
00
#11500
b1100 "
1/
b1100 #
1!
10
#12000
0!
00
#12500
b1101 #
b1101 "
1!
10
#13000
0!
00
#13500
b1110 "
0/
b1110 #
1!
10
#14000
0!
00
#14500
b1111 #
1/
b1111 "
1!
10
#15000
0!
00
#15500
b10000 "
0/
b10000 #
1!
10
#16000
0!
00
#16500
b10001 #
1/
b10001 "
1!
10
#17000
0!
00
#17500
b10010 "
0/
b10010 #
1!
10
#18000
0!
00
#18500
b10 ;
b11 :
b111 9
11
1=
b11111111111111111111111111110110 >
1<
b10011 #
1/
b10011 "
b1 ,
b1 $
b1 -
b1 &
b11111111111111111111111111111101 *
b11111111111111111111111111111101 4
b11111111111111111111111111111001 )
b11111111111111111111111111111001 3
1!
10
#19000
0!
00
#19500
01
b0 ,
b0 $
b0 -
b0 &
b10100 "
b10100 #
1@
17
b11111111111111111111111111110110 ?
b11111111111111111111111111110110 6
1!
10
#20000
0!
00
#20500
0@
07
b10101 #
0/
b10101 "
1!
10
#21000
0!
00
#21500
11
b1 2
b1 &
b1 '
b10110 "
1/
b10110 #
1!
10
#22000
0!
00
#22500
01
1@
17
b10111 #
0/
b10111 "
b0 &
1!
10
#23000
0!
00
#23500
b11000 "
b11000 #
0@
07
1!
10
#24000
0!
00
#24500
b11111111111111111111111111111100 >
11
b10 2
b11001 #
b11001 "
b1 &
b10 '
1!
10
#25000
0!
00
#25500
01
b0 &
b11010 "
1/
b11010 #
1@
17
b11111111111111111111111111111100 ?
b11111111111111111111111111111100 6
1!
10
#26000
0!
00
#26500
0@
07
b11011 #
0/
b11011 "
1!
10
#27000
0!
00
#27500
11
b11 2
b1 &
b11 '
b11100 "
1/
b11100 #
1!
10
#28000
0!
00
#28500
01
1@
17
b11101 #
b11101 "
b0 &
1!
10
#29000
0!
00
#29500
b11110 "
b11110 #
0@
07
1!
10
#30000
0!
00
#30500
b10101 >
11
b100 2
b11111 #
b11111 "
b1 &
b100 '
1!
10
#31000
0!
00
#31500
01
b0 &
b100000 "
0/
b100000 #
1@
17
b10101 ?
b10101 6
1!
10
#32000
0!
00
#32500
0@
07
b100001 #
b100001 "
1!
10
#33000
0!
00
#33500
11
b101 2
b1 &
b101 '
b100010 "
b100010 #
1!
10
#34000
0!
00
#34500
01
1@
17
b100011 #
b100011 "
b0 &
1!
10
#35000
0!
00
#35500
b100100 "
1/
b100100 #
0@
07
1!
10
#36000
0!
00
#36500
b10 >
11
b110 2
b100101 #
0/
b100101 "
b1 &
b110 '
1!
10
#37000
0!
00
#37500
01
b0 &
b100110 "
1/
b100110 #
1@
17
b10 ?
b10 6
1!
10
#38000
0!
00
#38500
0@
07
b100111 #
b100111 "
1!
10
#39000
0!
00
#39500
b0 >
11
b111 2
b1 &
b111 '
b101000 "
b101000 #
1!
10
#40000
0!
00
#40500
01
b0 ?
b0 6
1@
17
b101001 #
b101001 "
b0 &
1!
10
#41000
0!
00
#41500
b101010 "
b101010 #
0@
07
1!
10
#42000
0!
00
#42500
11
b1000 2
b101011 #
0/
b101011 "
b1 &
b1000 '
1!
10
#43000
0!
00
#43500
01
b0 &
b101100 "
b101100 #
1@
17
1!
10
#44000
0!
00
#44500
0@
07
b101101 #
1/
b101101 "
1!
10
#45000
0!
00
#45500
11
b1001 2
b1 &
b1001 '
b101110 "
b101110 #
1!
10
#46000
0!
00
#46500
01
1@
17
b101111 #
b101111 "
b0 &
1!
10
#47000
0!
00
#47500
b110000 "
0/
b110000 #
0@
07
1!
10
#48000
0!
00
#48500
11
b1010 2
b110001 #
b110001 "
b1 &
b1010 '
1!
10
#49000
0!
00
#49500
01
b0 &
b110010 "
b110010 #
1@
17
1!
10
#50000
0!
00
#50500
0@
07
b110011 #
b110011 "
1!
10
#51000
0!
00
#51500
11
b1011 2
b1 &
b1011 '
b110100 "
b110100 #
1!
10
#52000
0!
00
#52500
01
1@
17
b110101 #
1/
b110101 "
b0 &
1!
10
#53000
0!
00
#53500
b110110 "
0/
b110110 #
0@
07
1!
10
#54000
0!
00
#54500
11
b1100 2
b110111 #
b110111 "
b1 &
b1100 '
1!
10
#55000
0!
00
#55500
01
b0 &
b111000 "
1/
b111000 #
1@
17
1!
10
#56000
0!
00
#56500
0@
07
b111001 #
b111001 "
1!
10
#57000
0!
00
#57500
11
b1101 2
b1 &
b1101 '
b111010 "
0/
b111010 #
1!
10
#58000
0!
00
#58500
01
1@
17
b111011 #
b111011 "
b0 &
1!
10
#59000
0!
00
#59500
b111100 "
b111100 #
0@
07
1!
10
#60000
0!
00
#60500
11
b1110 2
b111101 #
b111101 "
b1 &
b1110 '
1!
10
#61000
0!
00
#61500
01
b0 &
b111110 "
b111110 #
1@
17
1!
10
#62000
0!
00
#62500
0@
07
b111111 #
1/
b111111 "
1!
10
#63000
0!
00
#63500
11
b1111 2
b1 &
b1111 '
b1000000 "
b1000000 #
1!
10
#64000
0!
00
#64500
01
1@
17
b1000001 #
b1000001 "
b0 &
1!
10
#65000
0!
00
#65500
b1000010 "
b1000010 #
0@
07
1!
10
#66000
0!
00
#66500
b0 :
bx ;
b0 9
b0 2
0=
0<
b1000011 #
b1000011 "
b11111111111111111111111111111001 ,
b0 '
b0 *
b0 4
b0 )
b0 3
1!
10
#67000
0!
00
#67500
b11111111111111111111111111111101 ,
b1000100 "
0/
b1000100 #
1!
10
#68000
0!
00
#68500
b10 ;
b11 :
b111 9
11
b1 5
1=
b11111111111111111111111111111001 >
1<
b1000101 #
b1000101 "
b0 ,
b1 &
b1 +
b11111111111111111111111111111101 *
b11111111111111111111111111111101 4
b11111111111111111111111111111001 )
b11111111111111111111111111111001 3
1!
10
#69000
0!
00
#69500
01
b0 &
b1000110 "
1/
b1000110 #
1@
17
b11111111111111111111111111111001 ?
b11111111111111111111111111111001 6
1!
10
#70000
0!
00
#70500
0@
07
b1000111 #
b1000111 "
1!
10
#71000
0!
00
#71500
b11111111111111111111111111111101 >
11
b1 2
b1 &
b1 '
b1001000 "
b1001000 #
1!
10
#72000
0!
00
#72500
01
b11111111111111111111111111111101 ?
b11111111111111111111111111111101 6
1@
17
b1001001 #
0/
b1001001 "
b0 &
1!
10
#73000
0!
00
#73500
b1001010 "
b1001010 #
0@
07
1!
10
#74000
0!
00
#74500
b100 >
11
b10 2
b1001011 #
1/
b1001011 "
b1 &
b10 '
1!
10
#75000
0!
00
#75500
01
b0 &
b1001100 "
b1001100 #
1@
17
b100 ?
b100 6
1!
10
#76000
0!
00
#76500
0@
07
b1001101 #
0/
b1001101 "
1!
10
#77000
0!
00
#77500
b0 >
11
b11 2
b1 &
b11 '
b1001110 "
1/
b1001110 #
1!
10
#78000
0!
00
#78500
01
b0 ?
b0 6
1@
17
b1001111 #
b1001111 "
b0 &
1!
10
#79000
0!
00
#79500
b1010000 "
0/
b1010000 #
0@
07
1!
10
#80000
0!
00
#80500
11
b100 2
b1010001 #
1/
b1010001 "
b1 &
b100 '
1!
10
#81000
0!
00
#81500
01
b0 &
b1010010 "
b1010010 #
1@
17
1!
10
#82000
0!
00
#82500
0@
07
b1010011 #
b1010011 "
1!
10
#83000
0!
00
#83500
11
b101 2
b1 &
b101 '
b1010100 "
0/
b1010100 #
1!
10
#84000
0!
00
#84500
01
1@
17
b1010101 #
1/
b1010101 "
b0 &
1!
10
#85000
0!
00
#85500
b1010110 "
b1010110 #
0@
07
1!
10
#86000
0!
00
#86500
11
b110 2
b1010111 #
0/
b1010111 "
b1 &
b110 '
1!
10
#87000
0!
00
#87500
01
b0 &
b1011000 "
b1011000 #
1@
17
1!
10
#88000
0!
00
#88500
0@
07
b1011001 #
b1011001 "
1!
10
#89000
0!
00
#89500
11
b111 2
b1 &
b111 '
b1011010 "
b1011010 #
1!
10
#90000
0!
00
#90500
01
1@
17
b1011011 #
1/
b1011011 "
b0 &
1!
10
#91000
0!
00
#91500
b1011100 "
b1011100 #
0@
07
1!
10
#92000
0!
00
#92500
11
b1000 2
b1011101 #
0/
b1011101 "
b1 &
b1000 '
1!
10
#93000
0!
00
#93500
01
b0 &
b1011110 "
b1011110 #
1@
17
1!
10
#94000
0!
00
#94500
0@
07
b1011111 #
1/
b1011111 "
1!
10
#95000
0!
00
#95500
11
b1001 2
b1 &
b1001 '
b1100000 "
b1100000 #
1!
10
#96000
0!
00
#96500
01
1@
17
b1100001 #
b1100001 "
b0 &
1!
10
#97000
0!
00
#97500
b1100010 "
b1100010 #
0@
07
1!
10
#98000
0!
00
#98500
11
b1010 2
b1100011 #
b1100011 "
b1 &
b1010 '
1!
10
#99000
0!
00
#99500
01
b0 &
b1100100 "
0/
b1100100 #
1@
17
1!
10
#100000
0!
00
#100500
0@
07
b1100101 #
1/
b1100101 "
1!
10
#101000
0!
00
#101500
11
b1011 2
b1 &
b1011 '
b1100110 "
b1100110 #
1!
10
#102000
0!
00
#102500
01
1@
17
b1100111 #
b1100111 "
b0 &
1!
10
#103000
0!
00
#103500
b1101000 "
0/
b1101000 #
0@
07
1!
10
#104000
0!
00
#104500
11
b1100 2
b1101001 #
b1101001 "
b1 &
b1100 '
1!
10
#105000
0!
00
#105500
01
b0 &
b1101010 "
b1101010 #
1@
17
1!
10
#106000
0!
00
#106500
0@
07
b1101011 #
b1101011 "
1!
10
#107000
0!
00
#107500
11
b1101 2
b1 &
b1101 '
b1101100 "
b1101100 #
1!
10
#108000
0!
00
#108500
01
1@
17
b1101101 #
b1101101 "
b0 &
1!
10
#109000
0!
00
#109500
b1101110 "
b1101110 #
0@
07
1!
10
#110000
0!
00
