define.v
////////////////////////////////
// modakio cpu operation number
// operation number

// func log2
//function integer log2;
//	input integer in;
//	begin
//		in = in - 1;
//		for (log2 = 0; in > 0; log2 = log2+1)
//			in = in >> 1;
//	end
//endfunction



// 
// CalcReg(CR)
// 
`define TYPE_CR		0
// interger
`define	OP_IADD		0
`define	OP_UIADD	1
`define	OP_ISUB		2
`define	OP_UISUB	3
`define	OP_IMUL		4
`define	OP_UIMUL	5
`define	OP_IDEV		6
`define	OP_UIDEV	7

//floating point 
`define	OP_FADD		8
`define	OP_FCMP		9
`define	OP_FSUB		10
`define	OP_CR_NOUSE11	11
`define	OP_FMUL		12
`define	OP_CR_NOUSE13	13
`define	OP_FDEV		14
`define	OP_CR_NOUSE15	15

// 
// LogicReg(LR)
// 
`define TYPE_LR		1

// bit logical

`define	OP_AND		0
`define	OP_OR		1
`define	OP_XOR		2
`define	OP_UCMP		3
`define	OP_LSFT		4
`define	OP_RSFT		5
`define	OP_CMP		6
`define	OP_JR		7

`define	OP_LR_NOUSE8	8
`define	OP_LR_NOUSE9	9
`define	OP_LR_NOUSE10	10
`define	OP_LR_NOUSE11	11
`define	OP_LR_NOUSE12	12
`define	OP_LR_NOUSE13	13
`define	OP_LR_NOUSE14	14
`define	OP_LR_NOUSE15	15


// 
// Immediate
// 
`define TYPE_I		2

`define	OP_IADDI	0
`define	OP_UIADDI	1
`define	OP_ISUBI	2
`define	OP_UISUBI	3
`define	OP_IMULI	4
`define	OP_UIMULI	5
`define	OP_IDEVI	6
`define	OP_UIDEVI	7

`define	OP_LW		8
`define	OP_ST		9
`define	OP_LSFTI	10
`define	OP_RSFTI	11
`define	OP_BE		12
`define	OP_BNE		13
`define	OP_CMPI		14
`define	OP_UCMPI	15


// 
// Jump
// 
`define TYPE_J		3

`define	OP_J		0
`define	OP_JAL		1
`define	OP_J_NOUSE2	2
`define	OP_J_NOUSE3	3
`define	OP_J_NOUSE4	4
`define	OP_J_NOUSE5	5
`define	OP_J_NOUSE6	6
`define	OP_J_NOUSE7	7

`define	OP_J_NOUSE8	8
`define	OP_J_NOUSE9	9
`define	OP_J_NOUSE10	10
`define	OP_J_NOUSE11	11
`define	OP_J_NOUSE12	12
`define	OP_J_NOUSE13	13
`define	OP_J_NOUSE14	14
`define	OP_J_NOUSE15	15

`define	NUM_OF_OP	42

//
// HARDWARE DISCRIPTION
//
`define	NUM_OF_FETCH_INST	4
`define	INST_FIFO_LENGTH	`NUM_OF_FETCH_INST * 2

`define WORD_BITS	32
`define	NUM_OF_REG	32
`define REG_ADDR_BITS	5 
`define MEM_ADDR_BITS	18

`define BITS_PER_BYTE	8

`define INST_BITS	`WORD_BITS
`define TYPE_BITS	2
`define OP_BITS		4
`define DST_BITS	5
`define SRC0_BITS	5
`define SRC1_BITS	5
`define MINOR_IMM_BITS	16
`define MAJOR_IMM_BITS	26

`define TYPE_OFFSET	`INST_BITS - `TYPE_BITS
`define OP_OFFSET	`INST_BITS - `TYPE_BITS - `OP_BITS
`define DST_OFFSET	`INST_BITS - `TYPE_BITS - `OP_BITS - `DST_BITS
`define SRC0_OFFSET	`INST_BITS - `TYPE_BITS - `OP_BITS - `DST_BITS - `SRC0_BITS
`define SRC1_OFFSET	`INST_BITS - `TYPE_BITS - `OP_BITS - `DST_BITS - `SRC0_BITS - `SRC1_BITS
`define MINOR_IMM_OFFSET	`INST_BITS - `TYPE_BITS - `OP_BITS - `DST_BITS - `SRC0_BITS - `MINOR_IMM_BITS
`define MAJOR_IMM_OFFSET	`INST_BITS - `TYPE_BITS - `OP_BITS - `MAJOR_IMM_BITS

`define BURST_LENGTH	4

arb5/mArb5.v
///////////////////////////////////////////
// This modules is in modakio cpu.
// mArb5.v module ver 1.0
// 2019/03/11 writen by denchu
//
`ifndef	_mARB5_
`define	_mARB5_
`include	"./define.v"

module mArb5 #(
	parameter			p_st_bits = `WORD_BITS
)(
	input	[p_st_bits-1:0]	iSnk0Data,
	input			iSnk0Valid,
	input	[p_st_bits-1:0]	iSnk1Data,
	input			iSnk1Valid,
	input	[p_st_bits-1:0]	iSnk2Data,
	input			iSnk2Valid,
	input	[p_st_bits-1:0]	iSnk3Data,
	input			iSnk3Valid,
	input	[p_st_bits-1:0]	iSnk4Data,
	input			iSnk4Valid,
	
	output	[p_st_bits-1:0]	oSrc0Data,
	output			oSrc0Valid,
	
	input	rst,
	input	clk
); 

	assign oSrc0Data	=	(iSnk0Valid == 1'b1)? iSnk0Data : 
					(iSnk1Valid == 1'b1)? iSnk1Data : 
					(iSnk2Valid == 1'b1)? iSnk2Data : 
					(iSnk3Valid == 1'b1)? iSnk3Data :
					(iSnk4Valid == 1'b1)? iSnk4Data : 0;
	assign oSrc0Valid	=	(((iSnk0Valid | iSnk1Valid) | (iSnk2Valid | iSnk3Valid)))| iSnk4Valid;

endmodule

`endif

arb5/main.v
`timescale  1ns/1ns

`include "../define.v"
`define WORD_BITS 32

module main;
	reg rst;
	reg clk;
	reg [`WORD_BITS-1:0]	a;
	reg [`REG_ADDR_BITS-1:0]	addr;
	reg valid0;
	reg valid1;
	reg valid2;


	parameter CYCLE = 1000; //clock rate = 1000ns(1MHz)


	//reset
	initial begin
				rst = 1;
		#(CYCLE*4)	rst = 0;
	end

	//clock
	initial begin
		clk = 0;
		end
	always begin
		#(CYCLE/2) clk = ~clk;
	end
	
	//count up
	initial begin
		a = 0;
		end
		always @(posedge clk) begin
			a = a + 1;
		end

	initial begin

		$dumpfile("main.vcd");
		$dumpvars(0, main);
				valid0 	<= 0;
				valid1 	<= 0;
				valid2 	<= 0;
		#(CYCLE*100)
				valid0 	<= 1;
				valid1 	<= 0;
				valid2 	<= 0;
		#(CYCLE*100)
				valid0 	<= 0;
				valid1 	<= 1;
				valid2 	<= 0;
		#(CYCLE*100)
				valid0 	<= 0;
				valid1 	<= 0;
				valid2 	<= 1;
		#(CYCLE*100);
		$finish;
	end
	
	mArb5 uArb5(
		.iSnk0Data	(a),
		.iSnk0Valid	(valid0),
		.iSnk1Data	(a<<2),
		.iSnk1Valid	(valid1),
		.iSnk2Data	(a<<4),
		.iSnk2Valid	(valid2),
		
		.oSrc0Data	(),
		.oSrc0Valid	(),
		
		.rst		(rst),
		.clk		(clk)
	); 

endmodule

arb5/main.vcd
$date
	Tue Mar 12 22:16:14 2019
$end
$version
	Icarus Verilog
$end
$timescale
	1ns
$end
$scope module main $end
$var reg 32 ! a [31:0] $end
$var reg 1 " clk $end
$var reg 1 # rst $end
$var reg 1 $ valid0 $end
$var reg 1 % valid1 $end
$var reg 1 & valid2 $end
$scope module uArb $end
$var wire 1 ' clk $end
$var wire 32 ( iSnk0Data [31:0] $end
$var wire 1 ) iSnk0Valid $end
$var wire 32 * iSnk1Data [31:0] $end
$var wire 1 + iSnk1Valid $end
$var wire 32 , iSnk2Data [31:0] $end
$var wire 1 - iSnk2Valid $end
$var wire 32 . oSrc0Data [31:0] $end
$var wire 1 / oSrc0Valid $end
$var wire 1 0 rst $end
$upscope $end
$upscope $end
$enddefinitions $end
#0
$dumpvars
10
0/
b0 .
0-
b0 ,
0+
b0 *
0)
b0 (
0'
0&
0%
0$
1#
0"
b0 !
$end
#500
b100 *
b10000 ,
b1 !
b1 (
1"
1'
#1000
0"
0'
#1500
b1000 *
b100000 ,
b10 !
b10 (
1"
1'
#2000
0"
0'
#2500
b1100 *
b110000 ,
b11 !
b11 (
1"
1'
#3000
0"
0'
#3500
b10000 *
b1000000 ,
b100 !
b100 (
1"
1'
#4000
0"
0'
0#
00
#4500
b10100 *
b1010000 ,
b101 !
b101 (
1"
1'
#5000
0"
0'
#5500
b11000 *
b1100000 ,
b110 !
b110 (
1"
1'
#6000
0"
0'
#6500
b11100 *
b1110000 ,
b111 !
b111 (
1"
1'
#7000
0"
0'
#7500
b100000 *
b10000000 ,
b1000 !
b1000 (
1"
1'
#8000
0"
0'
#8500
b100100 *
b10010000 ,
b1001 !
b1001 (
1"
1'
#9000
0"
0'
#9500
b101000 *
b10100000 ,
b1010 !
b1010 (
1"
1'
#10000
0"
0'
#10500
b101100 *
b10110000 ,
b1011 !
b1011 (
1"
1'
#11000
0"
0'
#11500
b110000 *
b11000000 ,
b1100 !
b1100 (
1"
1'
#12000
0"
0'
#12500
b110100 *
b11010000 ,
b1101 !
b1101 (
1"
1'
#13000
0"
0'
#13500
b111000 *
b11100000 ,
b1110 !
b1110 (
1"
1'
#14000
0"
0'
#14500
b111100 *
b11110000 ,
b1111 !
b1111 (
1"
1'
#15000
0"
0'
#15500
b1000000 *
b100000000 ,
b10000 !
b10000 (
1"
1'
#16000
0"
0'
#16500
b1000100 *
b100010000 ,
b10001 !
b10001 (
1"
1'
#17000
0"
0'
#17500
b1001000 *
b100100000 ,
b10010 !
b10010 (
1"
1'
#18000
0"
0'
#18500
b1001100 *
b100110000 ,
b10011 !
b10011 (
1"
1'
#19000
0"
0'
#19500
b1010000 *
b101000000 ,
b10100 !
b10100 (
1"
1'
#20000
0"
0'
#20500
b1010100 *
b101010000 ,
b10101 !
b10101 (
1"
1'
#21000
0"
0'
#21500
b1011000 *
b101100000 ,
b10110 !
b10110 (
1"
1'
#22000
0"
0'
#22500
b1011100 *
b101110000 ,
b10111 !
b10111 (
1"
1'
#23000
0"
0'
#23500
b1100000 *
b110000000 ,
b11000 !
b11000 (
1"
1'
#24000
0"
0'
#24500
b1100100 *
b110010000 ,
b11001 !
b11001 (
1"
1'
#25000
0"
0'
#25500
b1101000 *
b110100000 ,
b11010 !
b11010 (
1"
1'
#26000
0"
0'
#26500
b1101100 *
b110110000 ,
b11011 !
b11011 (
1"
1'
#27000
0"
0'
#27500
b1110000 *
b111000000 ,
b11100 !
b11100 (
1"
1'
#28000
0"
0'
#28500
b1110100 *
b111010000 ,
b11101 !
b11101 (
1"
1'
#29000
0"
0'
#29500
b1111000 *
b111100000 ,
b11110 !
b11110 (
1"
1'
#30000
0"
0'
#30500
b1111100 *
b111110000 ,
b11111 !
b11111 (
1"
1'
#31000
0"
0'
#31500
b10000000 *
b1000000000 ,
b100000 !
b100000 (
1"
1'
#32000
0"
0'
#32500
b10000100 *
b1000010000 ,
b100001 !
b100001 (
1"
1'
#33000
0"
0'
#33500
b10001000 *
b1000100000 ,
b100010 !
b100010 (
1"
1'
#34000
0"
0'
#34500
b10001100 *
b1000110000 ,
b100011 !
b100011 (
1"
1'
#35000
0"
0'
#35500
b10010000 *
b1001000000 ,
b100100 !
b100100 (
1"
1'
#36000
0"
0'
#36500
b10010100 *
b1001010000 ,
b100101 !
b100101 (
1"
1'
#37000
0"
0'
#37500
b10011000 *
b1001100000 ,
b100110 !
b100110 (
1"
1'
#38000
0"
0'
#38500
b10011100 *
b1001110000 ,
b100111 !
b100111 (
1"
1'
#39000
0"
0'
#39500
b10100000 *
b1010000000 ,
b101000 !
b101000 (
1"
1'
#40000
0"
0'
#40500
b10100100 *
b1010010000 ,
b101001 !
b101001 (
1"
1'
#41000
0"
0'
#41500
b10101000 *
b1010100000 ,
b101010 !
b101010 (
1"
1'
#42000
0"
0'
#42500
b10101100 *
b1010110000 ,
b101011 !
b101011 (
1"
1'
#43000
0"
0'
#43500
b10110000 *
b1011000000 ,
b101100 !
b101100 (
1"
1'
#44000
0"
0'
#44500
b10110100 *
b1011010000 ,
b101101 !
b101101 (
1"
1'
#45000
0"
0'
#45500
b10111000 *
b1011100000 ,
b101110 !
b101110 (
1"
1'
#46000
0"
0'
#46500
b10111100 *
b1011110000 ,
b101111 !
b101111 (
1"
1'
#47000
0"
0'
#47500
b11000000 *
b1100000000 ,
b110000 !
b110000 (
1"
1'
#48000
0"
0'
#48500
b11000100 *
b1100010000 ,
b110001 !
b110001 (
1"
1'
#49000
0"
0'
#49500
b11001000 *
b1100100000 ,
b110010 !
b110010 (
1"
1'
#50000
0"
0'
#50500
b11001100 *
b1100110000 ,
b110011 !
b110011 (
1"
1'
#51000
0"
0'
#51500
b11010000 *
b1101000000 ,
b110100 !
b110100 (
1"
1'
#52000
0"
0'
#52500
b11010100 *
b1101010000 ,
b110101 !
b110101 (
1"
1'
#53000
0"
0'
#53500
b11011000 *
b1101100000 ,
b110110 !
b110110 (
1"
1'
#54000
0"
0'
#54500
b11011100 *
b1101110000 ,
b110111 !
b110111 (
1"
1'
#55000
0"
0'
#55500
b11100000 *
b1110000000 ,
b111000 !
b111000 (
1"
1'
#56000
0"
0'
#56500
b11100100 *
b1110010000 ,
b111001 !
b111001 (
1"
1'
#57000
0"
0'
#57500
b11101000 *
b1110100000 ,
b111010 !
b111010 (
1"
1'
#58000
0"
0'
#58500
b11101100 *
b1110110000 ,
b111011 !
b111011 (
1"
1'
#59000
0"
0'
#59500
b11110000 *
b1111000000 ,
b111100 !
b111100 (
1"
1'
#60000
0"
0'
#60500
b11110100 *
b1111010000 ,
b111101 !
b111101 (
1"
1'
#61000
0"
0'
#61500
b11111000 *
b1111100000 ,
b111110 !
b111110 (
1"
1'
#62000
0"
0'
#62500
b11111100 *
b1111110000 ,
b111111 !
b111111 (
1"
1'
#63000
0"
0'
#63500
b100000000 *
b10000000000 ,
b1000000 !
b1000000 (
1"
1'
#64000
0"
0'
#64500
b100000100 *
b10000010000 ,
b1000001 !
b1000001 (
1"
1'
#65000
0"
0'
#65500
b100001000 *
b10000100000 ,
b1000010 !
b1000010 (
1"
1'
#66000
0"
0'
#66500
b100001100 *
b10000110000 ,
b1000011 !
b1000011 (
1"
1'
#67000
0"
0'
#67500
b100010000 *
b10001000000 ,
b1000100 !
b1000100 (
1"
1'
#68000
0"
0'
#68500
b100010100 *
b10001010000 ,
b1000101 !
b1000101 (
1"
1'
#69000
0"
0'
#69500
b100011000 *
b10001100000 ,
b1000110 !
b1000110 (
1"
1'
#70000
0"
0'
#70500
b100011100 *
b10001110000 ,
b1000111 !
b1000111 (
1"
1'
#71000
0"
0'
#71500
b100100000 *
b10010000000 ,
b1001000 !
b1001000 (
1"
1'
#72000
0"
0'
#72500
b100100100 *
b10010010000 ,
b1001001 !
b1001001 (
1"
1'
#73000
0"
0'
#73500
b100101000 *
b10010100000 ,
b1001010 !
b1001010 (
1"
1'
#74000
0"
0'
#74500
b100101100 *
b10010110000 ,
b1001011 !
b1001011 (
1"
1'
#75000
0"
0'
#75500
b100110000 *
b10011000000 ,
b1001100 !
b1001100 (
1"
1'
#76000
0"
0'
#76500
b100110100 *
b10011010000 ,
b1001101 !
b1001101 (
1"
1'
#77000
0"
0'
#77500
b100111000 *
b10011100000 ,
b1001110 !
b1001110 (
1"
1'
#78000
0"
0'
#78500
b100111100 *
b10011110000 ,
b1001111 !
b1001111 (
1"
1'
#79000
0"
0'
#79500
b101000000 *
b10100000000 ,
b1010000 !
b1010000 (
1"
1'
#80000
0"
0'
#80500
b101000100 *
b10100010000 ,
b1010001 !
b1010001 (
1"
1'
#81000
0"
0'
#81500
b101001000 *
b10100100000 ,
b1010010 !
b1010010 (
1"
1'
#82000
0"
0'
#82500
b101001100 *
b10100110000 ,
b1010011 !
b1010011 (
1"
1'
#83000
0"
0'
#83500
b101010000 *
b10101000000 ,
b1010100 !
b1010100 (
1"
1'
#84000
0"
0'
#84500
b101010100 *
b10101010000 ,
b1010101 !
b1010101 (
1"
1'
#85000
0"
0'
#85500
b101011000 *
b10101100000 ,
b1010110 !
b1010110 (
1"
1'
#86000
0"
0'
#86500
b101011100 *
b10101110000 ,
b1010111 !
b1010111 (
1"
1'
#87000
0"
0'
#87500
b101100000 *
b10110000000 ,
b1011000 !
b1011000 (
1"
1'
#88000
0"
0'
#88500
b101100100 *
b10110010000 ,
b1011001 !
b1011001 (
1"
1'
#89000
0"
0'
#89500
b101101000 *
b10110100000 ,
b1011010 !
b1011010 (
1"
1'
#90000
0"
0'
#90500
b101101100 *
b10110110000 ,
b1011011 !
b1011011 (
1"
1'
#91000
0"
0'
#91500
b101110000 *
b10111000000 ,
b1011100 !
b1011100 (
1"
1'
#92000
0"
0'
#92500
b101110100 *
b10111010000 ,
b1011101 !
b1011101 (
1"
1'
#93000
0"
0'
#93500
b101111000 *
b10111100000 ,
b1011110 !
b1011110 (
1"
1'
#94000
0"
0'
#94500
b101111100 *
b10111110000 ,
b1011111 !
b1011111 (
1"
1'
#95000
0"
0'
#95500
b110000000 *
b11000000000 ,
b1100000 !
b1100000 (
1"
1'
#96000
0"
0'
#96500
b110000100 *
b11000010000 ,
b1100001 !
b1100001 (
1"
1'
#97000
0"
0'
#97500
b110001000 *
b11000100000 ,
b1100010 !
b1100010 (
1"
1'
#98000
0"
0'
#98500
b110001100 *
b11000110000 ,
b1100011 !
b1100011 (
1"
1'
#99000
0"
0'
#99500
b110010000 *
b11001000000 ,
b1100100 !
b1100100 (
1"
1'
#100000
b1100100 .
1/
1$
1)
0"
0'
#100500
b110010100 *
b11001010000 ,
b1100101 .
b1100101 !
b1100101 (
1"
1'
#101000
0"
0'
#101500
b110011000 *
b11001100000 ,
b1100110 .
b1100110 !
b1100110 (
1"
1'
#102000
0"
0'
#102500
b110011100 *
b11001110000 ,
b1100111 .
b1100111 !
b1100111 (
1"
1'
#103000
0"
0'
#103500
b110100000 *
b11010000000 ,
b1101000 .
b1101000 !
b1101000 (
1"
1'
#104000
0"
0'
#104500
b110100100 *
b11010010000 ,
b1101001 .
b1101001 !
b1101001 (
1"
1'
#105000
0"
0'
#105500
b110101000 *
b11010100000 ,
b1101010 .
b1101010 !
b1101010 (
1"
1'
#106000
0"
0'
#106500
b110101100 *
b11010110000 ,
b1101011 .
b1101011 !
b1101011 (
1"
1'
#107000
0"
0'
#107500
b110110000 *
b11011000000 ,
b1101100 .
b1101100 !
b1101100 (
1"
1'
#108000
0"
0'
#108500
b110110100 *
b11011010000 ,
b1101101 .
b1101101 !
b1101101 (
1"
1'
#109000
0"
0'
#109500
b110111000 *
b11011100000 ,
b1101110 .
b1101110 !
b1101110 (
1"
1'
#110000
0"
0'
#110500
b110111100 *
b11011110000 ,
b1101111 .
b1101111 !
b1101111 (
1"
1'
#111000
0"
0'
#111500
b111000000 *
b11100000000 ,
b1110000 .
b1110000 !
b1110000 (
1"
1'
#112000
0"
0'
#112500
b111000100 *
b11100010000 ,
b1110001 .
b1110001 !
b1110001 (
1"
1'
#113000
0"
0'
#113500
b111001000 *
b11100100000 ,
b1110010 .
b1110010 !
b1110010 (
1"
1'
#114000
0"
0'
#114500
b111001100 *
b11100110000 ,
b1110011 .
b1110011 !
b1110011 (
1"
1'
#115000
0"
0'
#115500
b111010000 *
b11101000000 ,
b1110100 .
b1110100 !
b1110100 (
1"
1'
#116000
0"
0'
#116500
b111010100 *
b11101010000 ,
b1110101 .
b1110101 !
b1110101 (
1"
1'
#117000
0"
0'
#117500
b111011000 *
b11101100000 ,
b1110110 .
b1110110 !
b1110110 (
1"
1'
#118000
0"
0'
#118500
b111011100 *
b11101110000 ,
b1110111 .
b1110111 !
b1110111 (
1"
1'
#119000
0"
0'
#119500
b111100000 *
b11110000000 ,
b1111000 .
b1111000 !
b1111000 (
1"
1'
#120000
0"
0'
#120500
b111100100 *
b11110010000 ,
b1111001 .
b1111001 !
b1111001 (
1"
1'
#121000
0"
0'
#121500
b111101000 *
b11110100000 ,
b1111010 .
b1111010 !
b1111010 (
1"
1'
#122000
0"
0'
#122500
b111101100 *
b11110110000 ,
b1111011 .
b1111011 !
b1111011 (
1"
1'
#123000
0"
0'
#123500
b111110000 *
b11111000000 ,
b1111100 .
b1111100 !
b1111100 (
1"
1'
#124000
0"
0'
#124500
b111110100 *
b11111010000 ,
b1111101 .
b1111101 !
b1111101 (
1"
1'
#125000
0"
0'
#125500
b111111000 *
b11111100000 ,
b1111110 .
b1111110 !
b1111110 (
1"
1'
#126000
0"
0'
#126500
b111111100 *
b11111110000 ,
b1111111 .
b1111111 !
b1111111 (
1"
1'
#127000
0"
0'
#127500
b1000000000 *
b100000000000 ,
b10000000 .
b10000000 !
b10000000 (
1"
1'
#128000
0"
0'
#128500
b1000000100 *
b100000010000 ,
b10000001 .
b10000001 !
b10000001 (
1"
1'
#129000
0"
0'
#129500
b1000001000 *
b100000100000 ,
b10000010 .
b10000010 !
b10000010 (
1"
1'
#130000
0"
0'
#130500
b1000001100 *
b100000110000 ,
b10000011 .
b10000011 !
b10000011 (
1"
1'
#131000
0"
0'
#131500
b1000010000 *
b100001000000 ,
b10000100 .
b10000100 !
b10000100 (
1"
1'
#132000
0"
0'
#132500
b1000010100 *
b100001010000 ,
b10000101 .
b10000101 !
b10000101 (
1"
1'
#133000
0"
0'
#133500
b1000011000 *
b100001100000 ,
b10000110 .
b10000110 !
b10000110 (
1"
1'
#134000
0"
0'
#134500
b1000011100 *
b100001110000 ,
b10000111 .
b10000111 !
b10000111 (
1"
1'
#135000
0"
0'
#135500
b1000100000 *
b100010000000 ,
b10001000 .
b10001000 !
b10001000 (
1"
1'
#136000
0"
0'
#136500
b1000100100 *
b100010010000 ,
b10001001 .
b10001001 !
b10001001 (
1"
1'
#137000
0"
0'
#137500
b1000101000 *
b100010100000 ,
b10001010 .
b10001010 !
b10001010 (
1"
1'
#138000
0"
0'
#138500
b1000101100 *
b100010110000 ,
b10001011 .
b10001011 !
b10001011 (
1"
1'
#139000
0"
0'
#139500
b1000110000 *
b100011000000 ,
b10001100 .
b10001100 !
b10001100 (
1"
1'
#140000
0"
0'
#140500
b1000110100 *
b100011010000 ,
b10001101 .
b10001101 !
b10001101 (
1"
1'
#141000
0"
0'
#141500
b1000111000 *
b100011100000 ,
b10001110 .
b10001110 !
b10001110 (
1"
1'
#142000
0"
0'
#142500
b1000111100 *
b100011110000 ,
b10001111 .
b10001111 !
b10001111 (
1"
1'
#143000
0"
0'
#143500
b1001000000 *
b100100000000 ,
b10010000 .
b10010000 !
b10010000 (
1"
1'
#144000
0"
0'
#144500
b1001000100 *
b100100010000 ,
b10010001 .
b10010001 !
b10010001 (
1"
1'
#145000
0"
0'
#145500
b1001001000 *
b100100100000 ,
b10010010 .
b10010010 !
b10010010 (
1"
1'
#146000
0"
0'
#146500
b1001001100 *
b100100110000 ,
b10010011 .
b10010011 !
b10010011 (
1"
1'
#147000
0"
0'
#147500
b1001010000 *
b100101000000 ,
b10010100 .
b10010100 !
b10010100 (
1"
1'
#148000
0"
0'
#148500
b1001010100 *
b100101010000 ,
b10010101 .
b10010101 !
b10010101 (
1"
1'
#149000
0"
0'
#149500
b1001011000 *
b100101100000 ,
b10010110 .
b10010110 !
b10010110 (
1"
1'
#150000
0"
0'
#150500
b1001011100 *
b100101110000 ,
b10010111 .
b10010111 !
b10010111 (
1"
1'
#151000
0"
0'
#151500
b1001100000 *
b100110000000 ,
b10011000 .
b10011000 !
b10011000 (
1"
1'
#152000
0"
0'
#152500
b1001100100 *
b100110010000 ,
b10011001 .
b10011001 !
b10011001 (
1"
1'
#153000
0"
0'
#153500
b1001101000 *
b100110100000 ,
b10011010 .
b10011010 !
b10011010 (
1"
1'
#154000
0"
0'
#154500
b1001101100 *
b100110110000 ,
b10011011 .
b10011011 !
b10011011 (
1"
1'
#155000
0"
0'
#155500
b1001110000 *
b100111000000 ,
b10011100 .
b10011100 !
b10011100 (
1"
1'
#156000
0"
0'
#156500
b1001110100 *
b100111010000 ,
b10011101 .
b10011101 !
b10011101 (
1"
1'
#157000
0"
0'
#157500
b1001111000 *
b100111100000 ,
b10011110 .
b10011110 !
b10011110 (
1"
1'
#158000
0"
0'
#158500
b1001111100 *
b100111110000 ,
b10011111 .
b10011111 !
b10011111 (
1"
1'
#159000
0"
0'
#159500
b1010000000 *
b101000000000 ,
b10100000 .
b10100000 !
b10100000 (
1"
1'
#160000
0"
0'
#160500
b1010000100 *
b101000010000 ,
b10100001 .
b10100001 !
b10100001 (
1"
1'
#161000
0"
0'
#161500
b1010001000 *
b101000100000 ,
b10100010 .
b10100010 !
b10100010 (
1"
1'
#162000
0"
0'
#162500
b1010001100 *
b101000110000 ,
b10100011 .
b10100011 !
b10100011 (
1"
1'
#163000
0"
0'
#163500
b1010010000 *
b101001000000 ,
b10100100 .
b10100100 !
b10100100 (
1"
1'
#164000
0"
0'
#164500
b1010010100 *
b101001010000 ,
b10100101 .
b10100101 !
b10100101 (
1"
1'
#165000
0"
0'
#165500
b1010011000 *
b101001100000 ,
b10100110 .
b10100110 !
b10100110 (
1"
1'
#166000
0"
0'
#166500
b1010011100 *
b101001110000 ,
b10100111 .
b10100111 !
b10100111 (
1"
1'
#167000
0"
0'
#167500
b1010100000 *
b101010000000 ,
b10101000 .
b10101000 !
b10101000 (
1"
1'
#168000
0"
0'
#168500
b1010100100 *
b101010010000 ,
b10101001 .
b10101001 !
b10101001 (
1"
1'
#169000
0"
0'
#169500
b1010101000 *
b101010100000 ,
b10101010 .
b10101010 !
b10101010 (
1"
1'
#170000
0"
0'
#170500
b1010101100 *
b101010110000 ,
b10101011 .
b10101011 !
b10101011 (
1"
1'
#171000
0"
0'
#171500
b1010110000 *
b101011000000 ,
b10101100 .
b10101100 !
b10101100 (
1"
1'
#172000
0"
0'
#172500
b1010110100 *
b101011010000 ,
b10101101 .
b10101101 !
b10101101 (
1"
1'
#173000
0"
0'
#173500
b1010111000 *
b101011100000 ,
b10101110 .
b10101110 !
b10101110 (
1"
1'
#174000
0"
0'
#174500
b1010111100 *
b101011110000 ,
b10101111 .
b10101111 !
b10101111 (
1"
1'
#175000
0"
0'
#175500
b1011000000 *
b101100000000 ,
b10110000 .
b10110000 !
b10110000 (
1"
1'
#176000
0"
0'
#176500
b1011000100 *
b101100010000 ,
b10110001 .
b10110001 !
b10110001 (
1"
1'
#177000
0"
0'
#177500
b1011001000 *
b101100100000 ,
b10110010 .
b10110010 !
b10110010 (
1"
1'
#178000
0"
0'
#178500
b1011001100 *
b101100110000 ,
b10110011 .
b10110011 !
b10110011 (
1"
1'
#179000
0"
0'
#179500
b1011010000 *
b101101000000 ,
b10110100 .
b10110100 !
b10110100 (
1"
1'
#180000
0"
0'
#180500
b1011010100 *
b101101010000 ,
b10110101 .
b10110101 !
b10110101 (
1"
1'
#181000
0"
0'
#181500
b1011011000 *
b101101100000 ,
b10110110 .
b10110110 !
b10110110 (
1"
1'
#182000
0"
0'
#182500
b1011011100 *
b101101110000 ,
b10110111 .
b10110111 !
b10110111 (
1"
1'
#183000
0"
0'
#183500
b1011100000 *
b101110000000 ,
b10111000 .
b10111000 !
b10111000 (
1"
1'
#184000
0"
0'
#184500
b1011100100 *
b101110010000 ,
b10111001 .
b10111001 !
b10111001 (
1"
1'
#185000
0"
0'
#185500
b1011101000 *
b101110100000 ,
b10111010 .
b10111010 !
b10111010 (
1"
1'
#186000
0"
0'
#186500
b1011101100 *
b101110110000 ,
b10111011 .
b10111011 !
b10111011 (
1"
1'
#187000
0"
0'
#187500
b1011110000 *
b101111000000 ,
b10111100 .
b10111100 !
b10111100 (
1"
1'
#188000
0"
0'
#188500
b1011110100 *
b101111010000 ,
b10111101 .
b10111101 !
b10111101 (
1"
1'
#189000
0"
0'
#189500
b1011111000 *
b101111100000 ,
b10111110 .
b10111110 !
b10111110 (
1"
1'
#190000
0"
0'
#190500
b1011111100 *
b101111110000 ,
b10111111 .
b10111111 !
b10111111 (
1"
1'
#191000
0"
0'
#191500
b1100000000 *
b110000000000 ,
b11000000 .
b11000000 !
b11000000 (
1"
1'
#192000
0"
0'
#192500
b1100000100 *
b110000010000 ,
b11000001 .
b11000001 !
b11000001 (
1"
1'
#193000
0"
0'
#193500
b1100001000 *
b110000100000 ,
b11000010 .
b11000010 !
b11000010 (
1"
1'
#194000
0"
0'
#194500
b1100001100 *
b110000110000 ,
b11000011 .
b11000011 !
b11000011 (
1"
1'
#195000
0"
0'
#195500
b1100010000 *
b110001000000 ,
b11000100 .
b11000100 !
b11000100 (
1"
1'
#196000
0"
0'
#196500
b1100010100 *
b110001010000 ,
b11000101 .
b11000101 !
b11000101 (
1"
1'
#197000
0"
0'
#197500
b1100011000 *
b110001100000 ,
b11000110 .
b11000110 !
b11000110 (
1"
1'
#198000
0"
0'
#198500
b1100011100 *
b110001110000 ,
b11000111 .
b11000111 !
b11000111 (
1"
1'
#199000
0"
0'
#199500
b1100100000 *
b110010000000 ,
b11001000 .
b11001000 !
b11001000 (
1"
1'
#200000
b1100100000 .
1%
1+
0$
0)
0"
0'
#200500
b1100100100 .
b1100100100 *
b110010010000 ,
b11001001 !
b11001001 (
1"
1'
#201000
0"
0'
#201500
b1100101000 .
b1100101000 *
b110010100000 ,
b11001010 !
b11001010 (
1"
1'
#202000
0"
0'
#202500
b1100101100 .
b1100101100 *
b110010110000 ,
b11001011 !
b11001011 (
1"
1'
#203000
0"
0'
#203500
b1100110000 .
b1100110000 *
b110011000000 ,
b11001100 !
b11001100 (
1"
1'
#204000
0"
0'
#204500
b1100110100 .
b1100110100 *
b110011010000 ,
b11001101 !
b11001101 (
1"
1'
#205000
0"
0'
#205500
b1100111000 .
b1100111000 *
b110011100000 ,
b11001110 !
b11001110 (
1"
1'
#206000
0"
0'
#206500
b1100111100 .
b1100111100 *
b110011110000 ,
b11001111 !
b11001111 (
1"
1'
#207000
0"
0'
#207500
b1101000000 .
b1101000000 *
b110100000000 ,
b11010000 !
b11010000 (
1"
1'
#208000
0"
0'
#208500
b1101000100 .
b1101000100 *
b110100010000 ,
b11010001 !
b11010001 (
1"
1'
#209000
0"
0'
#209500
b1101001000 .
b1101001000 *
b110100100000 ,
b11010010 !
b11010010 (
1"
1'
#210000
0"
0'
#210500
b1101001100 .
b1101001100 *
b110100110000 ,
b11010011 !
b11010011 (
1"
1'
#211000
0"
0'
#211500
b1101010000 .
b1101010000 *
b110101000000 ,
b11010100 !
b11010100 (
1"
1'
#212000
0"
0'
#212500
b1101010100 .
b1101010100 *
b110101010000 ,
b11010101 !
b11010101 (
1"
1'
